{
  "generated_at": "2026-07-17T15:02:19",
  "count": 114,
  "opportunities": [
    {
      "ticker": "AMD",
      "kind": "strategie_optimale",
      "strategy": "VENDRE put 415 + ACHETER put 410 exp 2026-07-31 (crédit ~1.30$)",
      "score": 100.0,
      "summary": "AMD : bull put spread 415/410 exp 2026-07-31 (14j) — crédit 1.30$, risque max 3.70$, POP 84%, EV prudent +0.38$/action, gain max 35% du risque en 14j",
      "details": {
        "strategie": "bull put spread",
        "jambes": [
          "VENDRE put 415",
          "ACHETER put 410"
        ],
        "expiry": "2026-07-31",
        "dte": 14,
        "credit_par_action": 1.3,
        "risque_max_par_action": 3.7,
        "prob_profit": 0.837,
        "esperance_gain_EV": 0.525,
        "edge_par_risque": 0.142,
        "ratio_gain_risque": 0.351,
        "rendement_annualise": 9.16,
        "kelly_pleine": 0.375,
        "demi_kelly_conseillee": 0.187,
        "spot": 485.12,
        "vol_estimee": 0.768,
        "iv_atm": 0.816,
        "ev_prudent_apres_frais": 0.375,
        "greeks": {
          "delta": 0.0163,
          "gamma": -0.0003,
          "theta_jour": 0.0484,
          "vega": -0.018
        }
      }
    },
    {
      "ticker": "AMD",
      "kind": "strategie_optimale",
      "strategy": "VENDRE put 425 + ACHETER put 420 exp 2026-07-31 (crédit ~1.62$)",
      "score": 100.0,
      "summary": "AMD : bull put spread 425/420 exp 2026-07-31 (14j) — crédit 1.62$, risque max 3.38$, POP 80%, EV prudent +0.46$/action, gain max 48% du risque en 14j",
      "details": {
        "strategie": "bull put spread",
        "jambes": [
          "VENDRE put 425",
          "ACHETER put 420"
        ],
        "expiry": "2026-07-31",
        "dte": 14,
        "credit_par_action": 1.62,
        "risque_max_par_action": 3.38,
        "prob_profit": 0.797,
        "esperance_gain_EV": 0.646,
        "edge_par_risque": 0.191,
        "ratio_gain_risque": 0.481,
        "rendement_annualise": 12.553,
        "kelly_pleine": 0.375,
        "demi_kelly_conseillee": 0.187,
        "spot": 485.12,
        "vol_estimee": 0.768,
        "iv_atm": 0.816,
        "ev_prudent_apres_frais": 0.463,
        "greeks": {
          "delta": 0.0189,
          "gamma": -0.0003,
          "theta_jour": 0.0483,
          "vega": -0.0181
        }
      }
    },
    {
      "ticker": "SPY",
      "kind": "strategie_optimale",
      "strategy": "VENDRE put 724 + ACHETER put 723 exp 2026-07-31 (crédit ~0.27$)",
      "score": 100.0,
      "summary": "SPY : bull put spread 724/723 exp 2026-07-31 (14j) — crédit 0.27$, risque max 0.73$, POP 86%, EV prudent +0.09$/action, gain max 36% du risque en 14j",
      "details": {
        "strategie": "bull put spread",
        "jambes": [
          "VENDRE put 724",
          "ACHETER put 723"
        ],
        "expiry": "2026-07-31",
        "dte": 14,
        "credit_par_action": 0.27,
        "risque_max_par_action": 0.73,
        "prob_profit": 0.857,
        "esperance_gain_EV": 0.139,
        "edge_par_risque": 0.189,
        "ratio_gain_risque": 0.361,
        "rendement_annualise": 9.4,
        "kelly_pleine": 0.46,
        "demi_kelly_conseillee": 0.23,
        "spot": 744.43,
        "vol_estimee": 0.133,
        "iv_atm": 0.152,
        "ev_prudent_apres_frais": 0.093,
        "greeks": {
          "delta": 0.0106,
          "gamma": -0.0006,
          "theta_jour": 0.0077,
          "vega": -0.0182
        }
      }
    },
    {
      "ticker": "SPY",
      "kind": "strategie_optimale",
      "strategy": "VENDRE put 730 + ACHETER put 729 exp 2026-07-31 (crédit ~0.29$)",
      "score": 100.0,
      "summary": "SPY : bull put spread 730/729 exp 2026-07-31 (14j) — crédit 0.29$, risque max 0.71$, POP 77%, EV prudent +0.04$/action, gain max 41% du risque en 14j",
      "details": {
        "strategie": "bull put spread",
        "jambes": [
          "VENDRE put 730",
          "ACHETER put 729"
        ],
        "expiry": "2026-07-31",
        "dte": 14,
        "credit_par_action": 0.29,
        "risque_max_par_action": 0.71,
        "prob_profit": 0.774,
        "esperance_gain_EV": 0.087,
        "edge_par_risque": 0.122,
        "ratio_gain_risque": 0.408,
        "rendement_annualise": 10.649,
        "kelly_pleine": 0.22,
        "demi_kelly_conseillee": 0.11,
        "spot": 744.43,
        "vol_estimee": 0.133,
        "iv_atm": 0.152,
        "ev_prudent_apres_frais": 0.038,
        "greeks": {
          "delta": 0.0145,
          "gamma": -0.0006,
          "theta_jour": 0.0073,
          "vega": -0.0181
        }
      }
    },
    {
      "ticker": "QQQ",
      "kind": "strategie_optimale",
      "strategy": "VENDRE put 655 + ACHETER put 653 exp 2026-07-31 (crédit ~0.40$)",
      "score": 100.0,
      "summary": "QQQ : bull put spread 655/653 exp 2026-07-31 (14j) — crédit 0.40$, risque max 1.60$, POP 87%, EV prudent +0.10$/action, gain max 25% du risque en 14j",
      "details": {
        "strategie": "bull put spread",
        "jambes": [
          "VENDRE put 655",
          "ACHETER put 653"
        ],
        "expiry": "2026-07-31",
        "dte": 14,
        "credit_par_action": 0.4,
        "risque_max_par_action": 1.6,
        "prob_profit": 0.867,
        "esperance_gain_EV": 0.156,
        "edge_par_risque": 0.098,
        "ratio_gain_risque": 0.25,
        "rendement_annualise": 6.518,
        "kelly_pleine": 0.336,
        "demi_kelly_conseillee": 0.168,
        "spot": 693.76,
        "vol_estimee": 0.26,
        "iv_atm": 0.254,
        "ev_prudent_apres_frais": 0.096,
        "greeks": {
          "delta": 0.0114,
          "gamma": -0.0004,
          "theta_jour": 0.0165,
          "vega": -0.0189
        }
      }
    },
    {
      "ticker": "QQQ",
      "kind": "strategie_optimale",
      "strategy": "VENDRE put 655 + ACHETER put 654 exp 2026-07-31 (crédit ~0.29$)",
      "score": 100.0,
      "summary": "QQQ : bull put spread 655/654 exp 2026-07-31 (14j) — crédit 0.29$, risque max 0.71$, POP 87%, EV prudent +0.12$/action, gain max 41% du risque en 14j",
      "details": {
        "strategie": "bull put spread",
        "jambes": [
          "VENDRE put 655",
          "ACHETER put 654"
        ],
        "expiry": "2026-07-31",
        "dte": 14,
        "credit_par_action": 0.29,
        "risque_max_par_action": 0.71,
        "prob_profit": 0.867,
        "esperance_gain_EV": 0.165,
        "edge_par_risque": 0.233,
        "ratio_gain_risque": 0.408,
        "rendement_annualise": 10.649,
        "kelly_pleine": 0.54,
        "demi_kelly_conseillee": 0.27,
        "spot": 693.76,
        "vol_estimee": 0.26,
        "iv_atm": 0.254,
        "ev_prudent_apres_frais": 0.116,
        "greeks": {
          "delta": 0.0058,
          "gamma": -0.0002,
          "theta_jour": 0.0083,
          "vega": -0.0095
        }
      }
    },
    {
      "ticker": "COIN",
      "kind": "strategie_optimale",
      "strategy": "VENDRE put 147 + ACHETER put 146 exp 2026-07-24 (crédit ~0.38$)",
      "score": 100.0,
      "summary": "COIN : bull put spread 147/146 exp 2026-07-24 (7j) — crédit 0.38$, risque max 0.62$, POP 73%, EV prudent +0.05$/action, gain max 60% du risque en 7j",
      "details": {
        "strategie": "bull put spread",
        "jambes": [
          "VENDRE put 147",
          "ACHETER put 146"
        ],
        "expiry": "2026-07-24",
        "dte": 7,
        "credit_par_action": 0.38,
        "risque_max_par_action": 0.62,
        "prob_profit": 0.728,
        "esperance_gain_EV": 0.109,
        "edge_par_risque": 0.175,
        "ratio_gain_risque": 0.6,
        "rendement_annualise": 31.286,
        "kelly_pleine": 0.275,
        "demi_kelly_conseillee": 0.137,
        "spot": 156.11,
        "vol_estimee": 0.691,
        "iv_atm": 0.843,
        "ev_prudent_apres_frais": 0.052,
        "greeks": {
          "delta": 0.0219,
          "gamma": -0.0011,
          "theta_jour": 0.0164,
          "vega": -0.0034
        }
      }
    },
    {
      "ticker": "COIN",
      "kind": "strategie_optimale",
      "strategy": "VENDRE put 149 + ACHETER put 148 exp 2026-07-24 (crédit ~0.53$)",
      "score": 100.0,
      "summary": "COIN : bull put spread 149/148 exp 2026-07-24 (7j) — crédit 0.53$, risque max 0.47$, POP 68%, EV prudent +0.14$/action, gain max 113% du risque en 7j",
      "details": {
        "strategie": "bull put spread",
        "jambes": [
          "VENDRE put 149",
          "ACHETER put 148"
        ],
        "expiry": "2026-07-24",
        "dte": 7,
        "credit_par_action": 0.53,
        "risque_max_par_action": 0.47,
        "prob_profit": 0.683,
        "esperance_gain_EV": 0.216,
        "edge_par_risque": 0.459,
        "ratio_gain_risque": 1.128,
        "rendement_annualise": 58.799,
        "kelly_pleine": 0.402,
        "demi_kelly_conseillee": 0.201,
        "spot": 156.11,
        "vol_estimee": 0.691,
        "iv_atm": 0.843,
        "ev_prudent_apres_frais": 0.143,
        "greeks": {
          "delta": 0.0237,
          "gamma": -0.0009,
          "theta_jour": 0.0142,
          "vega": -0.003
        }
      }
    },
    {
      "ticker": "PLTR",
      "kind": "strategie_optimale",
      "strategy": "VENDRE call 138 + ACHETER call 139 exp 2026-07-24 (crédit ~0.36$)",
      "score": 100.0,
      "summary": "PLTR : bear call spread 138/139 exp 2026-07-24 (7j) — crédit 0.36$, risque max 0.64$, POP 73%, EV prudent +0.03$/action, gain max 56% du risque en 7j",
      "details": {
        "strategie": "bear call spread",
        "jambes": [
          "VENDRE call 138",
          "ACHETER call 139"
        ],
        "expiry": "2026-07-24",
        "dte": 7,
        "credit_par_action": 0.36,
        "risque_max_par_action": 0.64,
        "prob_profit": 0.728,
        "esperance_gain_EV": 0.088,
        "edge_par_risque": 0.138,
        "ratio_gain_risque": 0.562,
        "rendement_annualise": 29.33,
        "kelly_pleine": 0.243,
        "demi_kelly_conseillee": 0.122,
        "spot": 131.91,
        "vol_estimee": 0.613,
        "iv_atm": 0.694,
        "ev_prudent_apres_frais": 0.032,
        "greeks": {
          "delta": -0.0296,
          "gamma": -0.0014,
          "theta_jour": 0.0128,
          "vega": -0.0028
        }
      }
    },
    {
      "ticker": "PFE",
      "kind": "strategie_optimale",
      "strategy": "VENDRE put 25 + ACHETER put 24 exp 2026-07-24 (crédit ~0.30$)",
      "score": 100.0,
      "summary": "PFE : bull put spread 25/24 exp 2026-07-24 (7j) — crédit 0.30$, risque max 0.70$, POP 76%, EV prudent +0.07$/action, gain max 44% du risque en 7j",
      "details": {
        "strategie": "bull put spread",
        "jambes": [
          "VENDRE put 25",
          "ACHETER put 24"
        ],
        "expiry": "2026-07-24",
        "dte": 7,
        "credit_par_action": 0.3,
        "risque_max_par_action": 0.7,
        "prob_profit": 0.758,
        "esperance_gain_EV": 0.12,
        "edge_par_risque": 0.173,
        "ratio_gain_risque": 0.439,
        "rendement_annualise": 22.883,
        "kelly_pleine": 0.206,
        "demi_kelly_conseillee": 0.103,
        "spot": 25.34,
        "vol_estimee": 0.261,
        "iv_atm": 0.261,
        "ev_prudent_apres_frais": 0.07,
        "greeks": {
          "delta": 0.2762,
          "gamma": -0.2667,
          "theta_jour": 0.0152,
          "vega": -0.0086
        }
      }
    },
    {
      "ticker": "PFE",
      "kind": "strategie_optimale",
      "strategy": "VENDRE put 25 + ACHETER put 24.5 exp 2026-07-24 (crédit ~0.22$)",
      "score": 100.0,
      "summary": "PFE : bull put spread 25/24.5 exp 2026-07-24 (7j) — crédit 0.22$, risque max 0.28$, POP 73%, EV prudent +0.05$/action, gain max 79% du risque en 7j",
      "details": {
        "strategie": "bull put spread",
        "jambes": [
          "VENDRE put 25",
          "ACHETER put 24.5"
        ],
        "expiry": "2026-07-24",
        "dte": 7,
        "credit_par_action": 0.22,
        "risque_max_par_action": 0.28,
        "prob_profit": 0.727,
        "esperance_gain_EV": 0.092,
        "edge_par_risque": 0.328,
        "ratio_gain_risque": 0.786,
        "rendement_annualise": 40.969,
        "kelly_pleine": 0.38,
        "demi_kelly_conseillee": 0.19,
        "spot": 25.34,
        "vol_estimee": 0.261,
        "iv_atm": 0.261,
        "ev_prudent_apres_frais": 0.05,
        "greeks": {
          "delta": 0.1731,
          "gamma": -0.1286,
          "theta_jour": 0.0072,
          "vega": -0.0041
        }
      }
    },
    {
      "ticker": "LCID",
      "kind": "skew_peur",
      "strategy": "Vendre des put spreads (la protection est surpayée) ou prudence sur le titre",
      "score": 100.0,
      "summary": "LCID : skew extrême, puts -5% à 166% vs calls +5% à 114% (+52.5 pts) — le marché paie très cher la peur",
      "details": {
        "expiry": "2026-08-07",
        "dte": 21,
        "put_iv": 1.6621,
        "call_iv": 1.1367,
        "skew_pts": 52.5
      }
    },
    {
      "ticker": "WBD",
      "kind": "prime_riche",
      "strategy": "Vente de prime : put cash-secured, covered call ou iron condor",
      "score": 100.0,
      "summary": "WBD : IV 57% vs vol réalisée 19% (ratio x2.93) — les options sont chères, avantage au vendeur",
      "details": {
        "iv_atm": 0.5698,
        "rv_20d": 0.1946,
        "ratio": 2.93
      }
    },
    {
      "ticker": "WBD",
      "kind": "skew_inverse",
      "strategy": "Signal rare : spéculation haussière agressive — surveiller un squeeze / call spreads",
      "score": 100.0,
      "summary": "WBD : skew INVERSÉ, calls +5% à 70% plus chers que puts -5% à 48% (-21.8 pts) — demande haussière anormale",
      "details": {
        "expiry": "2026-08-07",
        "dte": 21,
        "put_iv": 0.4819,
        "call_iv": 0.7002,
        "skew_pts": -21.8
      }
    },
    {
      "ticker": "TLRY",
      "kind": "prime_riche",
      "strategy": "Vente de prime : put cash-secured, covered call ou iron condor",
      "score": 100.0,
      "summary": "TLRY : IV 87% vs vol réalisée 36% (ratio x2.44) — les options sont chères, avantage au vendeur",
      "details": {
        "iv_atm": 0.873,
        "rv_20d": 0.3574,
        "ratio": 2.44
      }
    },
    {
      "ticker": "INTC",
      "kind": "skew_inverse",
      "strategy": "Signal rare : spéculation haussière agressive — surveiller un squeeze / call spreads",
      "score": 99.7,
      "summary": "INTC : skew INVERSÉ, calls +5% à 102% plus chers que puts -5% à 89% (-13.7 pts) — demande haussière anormale",
      "details": {
        "expiry": "2026-08-28",
        "dte": 42,
        "put_iv": 0.887,
        "call_iv": 1.0237,
        "skew_pts": -13.7
      }
    },
    {
      "ticker": "META",
      "kind": "skew_inverse",
      "strategy": "Signal rare : spéculation haussière agressive — surveiller un squeeze / call spreads",
      "score": 94.3,
      "summary": "META : skew INVERSÉ, calls +5% à 65% plus chers que puts -5% à 53% (-12.3 pts) — demande haussière anormale",
      "details": {
        "expiry": "2026-08-07",
        "dte": 21,
        "put_iv": 0.527,
        "call_iv": 0.6503,
        "skew_pts": -12.3
      }
    },
    {
      "ticker": "INTC",
      "kind": "put_cash_secured",
      "strategy": "Vendre put INTC 85 exp 2026-07-31 @ ~4.22$ (capital requis 8,500$)",
      "score": 92.8,
      "summary": "INTC : put 85 (14j, delta 0.29) rapporte ~125% annualisé, prob. de profit ~63%",
      "details": {
        "expiry": "2026-07-31",
        "dte": 14,
        "strike": 85.0,
        "mid": 4.22,
        "bid_vente": 4.1,
        "commission_incluse": 1.0,
        "delta": 0.29,
        "annual_yield": 1.254,
        "prob_profit": 0.63,
        "capital_requis": 8500,
        "greeks": {
          "delta": 0.2919,
          "gamma": -0.0179,
          "theta_jour": 0.2315
        }
      }
    },
    {
      "ticker": "RIOT",
      "kind": "put_cash_secured",
      "strategy": "Vendre put RIOT 17 exp 2026-08-07 @ ~1.09$ (capital requis 1,700$)",
      "score": 90.4,
      "summary": "RIOT : put 17 (21j, delta 0.32) rapporte ~104% annualisé, prob. de profit ~59%",
      "details": {
        "expiry": "2026-08-07",
        "dte": 21,
        "strike": 17.0,
        "mid": 1.09,
        "bid_vente": 1.03,
        "commission_incluse": 1.0,
        "delta": 0.32,
        "annual_yield": 1.043,
        "prob_profit": 0.59,
        "capital_requis": 1700,
        "greeks": {
          "delta": 0.3202,
          "gamma": -0.0821,
          "theta_jour": 0.0362
        }
      }
    },
    {
      "ticker": "AMD",
      "kind": "put_cash_secured",
      "strategy": "Vendre put AMD 465 exp 2026-07-31 @ ~22.52$ (capital requis 46,500$)",
      "score": 89.8,
      "summary": "AMD : put 465 (14j, delta 0.36) rapporte ~121% annualisé, prob. de profit ~58%",
      "details": {
        "expiry": "2026-07-31",
        "dte": 14,
        "strike": 465.0,
        "mid": 22.52,
        "bid_vente": 21.65,
        "commission_incluse": 1.0,
        "delta": 0.36,
        "annual_yield": 1.213,
        "prob_profit": 0.58,
        "capital_requis": 46500,
        "greeks": {
          "delta": 0.3618,
          "gamma": -0.0048,
          "theta_jour": 1.0246
        }
      }
    },
    {
      "ticker": "MARA",
      "kind": "put_cash_secured",
      "strategy": "Vendre put MARA 10 exp 2026-08-07 @ ~0.65$ (capital requis 1,000$)",
      "score": 89.2,
      "summary": "MARA : put 10 (21j, delta 0.34) rapporte ~104% annualisé, prob. de profit ~57%",
      "details": {
        "expiry": "2026-08-07",
        "dte": 21,
        "strike": 10.0,
        "mid": 0.65,
        "bid_vente": 0.61,
        "commission_incluse": 1.0,
        "delta": 0.34,
        "annual_yield": 1.043,
        "prob_profit": 0.57,
        "capital_requis": 1000,
        "greeks": {
          "delta": 0.3394,
          "gamma": -0.1522,
          "theta_jour": 0.0204
        }
      }
    },
    {
      "ticker": "COIN",
      "kind": "put_cash_secured",
      "strategy": "Vendre put COIN 150 exp 2026-08-07 @ ~9.10$ (capital requis 15,000$)",
      "score": 88.0,
      "summary": "COIN : put 150 (21j, delta 0.38) rapporte ~101% annualisé, prob. de profit ~55%",
      "details": {
        "expiry": "2026-08-07",
        "dte": 21,
        "strike": 150.0,
        "mid": 9.1,
        "bid_vente": 8.75,
        "commission_incluse": 1.0,
        "delta": 0.38,
        "annual_yield": 1.013,
        "prob_profit": 0.55,
        "capital_requis": 15000,
        "greeks": {
          "delta": 0.3752,
          "gamma": -0.0127,
          "theta_jour": 0.2607
        }
      }
    },
    {
      "ticker": "SNAP",
      "kind": "prime_riche",
      "strategy": "Vente de prime : put cash-secured, covered call ou iron condor",
      "score": 86.5,
      "summary": "SNAP : IV 88% vs vol réalisée 40% (ratio x2.21) — les options sont chères, avantage au vendeur",
      "details": {
        "iv_atm": 0.8789,
        "rv_20d": 0.398,
        "ratio": 2.21
      }
    },
    {
      "ticker": "SNAP",
      "kind": "skew_inverse",
      "strategy": "Signal rare : spéculation haussière agressive — surveiller un squeeze / call spreads",
      "score": 82.5,
      "summary": "SNAP : skew INVERSÉ, calls +5% à 93% plus chers que puts -5% à 83% (-9.4 pts) — demande haussière anormale",
      "details": {
        "expiry": "2026-08-07",
        "dte": 21,
        "put_iv": 0.832,
        "call_iv": 0.9258,
        "skew_pts": -9.4
      }
    },
    {
      "ticker": "PBR",
      "kind": "skew_inverse",
      "strategy": "Signal rare : spéculation haussière agressive — surveiller un squeeze / call spreads",
      "score": 82.5,
      "summary": "PBR : skew INVERSÉ, calls +5% à 60% plus chers que puts -5% à 51% (-9.4 pts) — demande haussière anormale",
      "details": {
        "expiry": "2026-08-07",
        "dte": 21,
        "put_iv": 0.5088,
        "call_iv": 0.6025,
        "skew_pts": -9.4
      }
    },
    {
      "ticker": "LCID",
      "kind": "put_cash_secured",
      "strategy": "Vendre put LCID 6.5 exp 2026-08-28 @ ~1.32$ (capital requis 650$)",
      "score": 80.2,
      "summary": "LCID : put 6.5 (42j, delta 0.37) rapporte ~156% annualisé, prob. de profit ~42%",
      "details": {
        "expiry": "2026-08-28",
        "dte": 42,
        "strike": 6.5,
        "mid": 1.32,
        "bid_vente": 1.18,
        "commission_incluse": 1.0,
        "delta": 0.37,
        "annual_yield": 1.564,
        "prob_profit": 0.42,
        "capital_requis": 650,
        "greeks": {
          "delta": 0.3695,
          "gamma": -0.1043,
          "theta_jour": 0.0158
        }
      }
    },
    {
      "ticker": "TSLA",
      "kind": "strategie_optimale",
      "strategy": "VENDRE put 367.5 + ACHETER put 362.5 exp 2026-07-24 (crédit ~2.00$)",
      "score": 80.0,
      "summary": "TSLA : bull put spread 367.5/362.5 exp 2026-07-24 (7j) — crédit 2.00$, risque max 3.00$, POP 68%, EV prudent +0.22$/action, gain max 67% du risque en 7j [ATTENTION : earnings avant l'expiration]",
      "details": {
        "strategie": "bull put spread",
        "jambes": [
          "VENDRE put 367.5",
          "ACHETER put 362.5"
        ],
        "expiry": "2026-07-24",
        "dte": 7,
        "credit_par_action": 2.0,
        "risque_max_par_action": 3.0,
        "prob_profit": 0.678,
        "esperance_gain_EV": 0.442,
        "edge_par_risque": 0.147,
        "ratio_gain_risque": 0.667,
        "rendement_annualise": 34.762,
        "kelly_pleine": 0.195,
        "demi_kelly_conseillee": 0.098,
        "spot": 380.0,
        "vol_estimee": 0.56,
        "iv_atm": 0.509,
        "ev_prudent_apres_frais": 0.222,
        "greeks": {
          "delta": 0.0598,
          "gamma": -0.0012,
          "theta_jour": 0.0686,
          "vega": -0.0179
        },
        "attention_earnings": "résultats dans 5j, avant l'expiration — risque de gap"
      }
    },
    {
      "ticker": "TSLA",
      "kind": "strategie_optimale",
      "strategy": "VENDRE put 367.5 + ACHETER put 365 exp 2026-07-24 (crédit ~1.25$)",
      "score": 80.0,
      "summary": "TSLA : bull put spread 367.5/365 exp 2026-07-24 (7j) — crédit 1.25$, risque max 1.25$, POP 67%, EV prudent +0.29$/action, gain max 100% du risque en 7j [ATTENTION : earnings avant l'expiration]",
      "details": {
        "strategie": "bull put spread",
        "jambes": [
          "VENDRE put 367.5",
          "ACHETER put 365"
        ],
        "expiry": "2026-07-24",
        "dte": 7,
        "credit_par_action": 1.25,
        "risque_max_par_action": 1.25,
        "prob_profit": 0.669,
        "esperance_gain_EV": 0.432,
        "edge_par_risque": 0.346,
        "ratio_gain_risque": 1.0,
        "rendement_annualise": 52.143,
        "kelly_pleine": 0.337,
        "demi_kelly_conseillee": 0.169,
        "spot": 380.0,
        "vol_estimee": 0.56,
        "iv_atm": 0.509,
        "ev_prudent_apres_frais": 0.287,
        "greeks": {
          "delta": 0.0306,
          "gamma": -0.0005,
          "theta_jour": 0.0322,
          "vega": -0.0084
        },
        "attention_earnings": "résultats dans 5j, avant l'expiration — risque de gap"
      }
    },
    {
      "ticker": "PLTR",
      "kind": "strategie_optimale",
      "strategy": "VENDRE put 113 + ACHETER put 112 exp 2026-08-07 (crédit ~0.24$)",
      "score": 80.0,
      "summary": "PLTR : bull put spread 113/112 exp 2026-08-07 (21j) — crédit 0.24$, risque max 0.76$, POP 84%, EV prudent +0.04$/action, gain max 32% du risque en 21j [ATTENTION : earnings avant l'expiration]",
      "details": {
        "strategie": "bull put spread",
        "jambes": [
          "VENDRE put 113",
          "ACHETER put 112"
        ],
        "expiry": "2026-08-07",
        "dte": 21,
        "credit_par_action": 0.24,
        "risque_max_par_action": 0.76,
        "prob_profit": 0.84,
        "esperance_gain_EV": 0.088,
        "edge_par_risque": 0.116,
        "ratio_gain_risque": 0.316,
        "rendement_annualise": 5.489,
        "kelly_pleine": 0.333,
        "demi_kelly_conseillee": 0.166,
        "spot": 131.91,
        "vol_estimee": 0.613,
        "iv_atm": 0.694,
        "ev_prudent_apres_frais": 0.044,
        "greeks": {
          "delta": 0.0121,
          "gamma": -0.0007,
          "theta_jour": 0.0063,
          "vega": -0.0045
        },
        "attention_earnings": "résultats dans 17j, avant l'expiration — risque de gap"
      }
    },
    {
      "ticker": "SOFI",
      "kind": "strategie_optimale",
      "strategy": "VENDRE put 14.5 + ACHETER put 14 exp 2026-08-28 (crédit ~0.15$)",
      "score": 80.0,
      "summary": "SOFI : bull put spread 14.5/14 exp 2026-08-28 (42j) — crédit 0.15$, risque max 0.35$, POP 78%, EV prudent +0.02$/action, gain max 45% du risque en 42j [ATTENTION : earnings avant l'expiration]",
      "details": {
        "strategie": "bull put spread",
        "jambes": [
          "VENDRE put 14.5",
          "ACHETER put 14"
        ],
        "expiry": "2026-08-28",
        "dte": 42,
        "credit_par_action": 0.15,
        "risque_max_par_action": 0.35,
        "prob_profit": 0.776,
        "esperance_gain_EV": 0.052,
        "edge_par_risque": 0.152,
        "ratio_gain_risque": 0.449,
        "rendement_annualise": 3.904,
        "kelly_pleine": 0.276,
        "demi_kelly_conseillee": 0.138,
        "spot": 16.84,
        "vol_estimee": 0.555,
        "iv_atm": 0.707,
        "ev_prudent_apres_frais": 0.017,
        "greeks": {
          "delta": 0.0447,
          "gamma": -0.0142,
          "theta_jour": 0.0016,
          "vega": -0.0026
        },
        "attention_earnings": "résultats dans 12j, avant l'expiration — risque de gap"
      }
    },
    {
      "ticker": "F",
      "kind": "strategie_optimale",
      "strategy": "VENDRE put 13.5 + ACHETER put 13 + VENDRE call 15.5 + ACHETER call 16 exp 2026-08-07 (crédit ~0.20$)",
      "score": 80.0,
      "summary": "F : iron condor 13.5/13/15.5/16 exp 2026-08-07 (21j) — crédit 0.20$, risque max 0.30$, POP 70%, EV prudent +0.02$/action, gain max 67% du risque en 21j [ATTENTION : earnings avant l'expiration]",
      "details": {
        "strategie": "iron condor",
        "jambes": [
          "VENDRE put 13.5",
          "ACHETER put 13",
          "VENDRE call 15.5",
          "ACHETER call 16"
        ],
        "expiry": "2026-08-07",
        "dte": 21,
        "credit_par_action": 0.2,
        "risque_max_par_action": 0.3,
        "prob_profit": 0.697,
        "esperance_gain_EV": 0.058,
        "edge_par_risque": 0.194,
        "ratio_gain_risque": 0.667,
        "rendement_annualise": 11.587,
        "kelly_pleine": 0.244,
        "demi_kelly_conseillee": 0.122,
        "spot": 14.32,
        "vol_estimee": 0.332,
        "iv_atm": 0.461,
        "ev_prudent_apres_frais": 0.018,
        "greeks": {
          "delta": 0.0241,
          "gamma": -0.1815,
          "theta_jour": 0.0055,
          "vega": -0.0071
        },
        "attention_earnings": "résultats dans 11j, avant l'expiration — risque de gap"
      }
    },
    {
      "ticker": "INTC",
      "kind": "strategie_optimale",
      "strategy": "VENDRE call 106 + ACHETER call 107 exp 2026-07-31 (crédit ~0.30$)",
      "score": 80.0,
      "summary": "INTC : bear call spread 106/107 exp 2026-07-31 (14j) — crédit 0.30$, risque max 0.70$, POP 81%, EV prudent +0.06$/action, gain max 43% du risque en 14j [ATTENTION : earnings avant l'expiration]",
      "details": {
        "strategie": "bear call spread",
        "jambes": [
          "VENDRE call 106",
          "ACHETER call 107"
        ],
        "expiry": "2026-07-31",
        "dte": 14,
        "credit_par_action": 0.3,
        "risque_max_par_action": 0.7,
        "prob_profit": 0.805,
        "esperance_gain_EV": 0.106,
        "edge_par_risque": 0.151,
        "ratio_gain_risque": 0.429,
        "rendement_annualise": 11.173,
        "kelly_pleine": 0.351,
        "demi_kelly_conseillee": 0.175,
        "spot": 93.01,
        "vol_estimee": 0.881,
        "iv_atm": 0.915,
        "ev_prudent_apres_frais": 0.056,
        "greeks": {
          "delta": -0.0171,
          "gamma": -0.0007,
          "theta_jour": 0.0069,
          "vega": -0.0021
        },
        "attention_earnings": "résultats dans 6j, avant l'expiration — risque de gap"
      }
    },
    {
      "ticker": "INTC",
      "kind": "strategie_optimale",
      "strategy": "VENDRE call 108 + ACHETER call 109 exp 2026-07-31 (crédit ~0.25$)",
      "score": 80.0,
      "summary": "INTC : bear call spread 108/109 exp 2026-07-31 (14j) — crédit 0.25$, risque max 0.75$, POP 83%, EV prudent +0.04$/action, gain max 33% du risque en 14j [ATTENTION : earnings avant l'expiration]",
      "details": {
        "strategie": "bear call spread",
        "jambes": [
          "VENDRE call 108",
          "ACHETER call 109"
        ],
        "expiry": "2026-07-31",
        "dte": 14,
        "credit_par_action": 0.25,
        "risque_max_par_action": 0.75,
        "prob_profit": 0.833,
        "esperance_gain_EV": 0.084,
        "edge_par_risque": 0.112,
        "ratio_gain_risque": 0.333,
        "rendement_annualise": 8.69,
        "kelly_pleine": 0.332,
        "demi_kelly_conseillee": 0.166,
        "spot": 93.01,
        "vol_estimee": 0.881,
        "iv_atm": 0.915,
        "ev_prudent_apres_frais": 0.039,
        "greeks": {
          "delta": -0.0155,
          "gamma": -0.0008,
          "theta_jour": 0.0072,
          "vega": -0.0023
        },
        "attention_earnings": "résultats dans 6j, avant l'expiration — risque de gap"
      }
    },
    {
      "ticker": "CLF",
      "kind": "strategie_optimale",
      "strategy": "VENDRE put 9 + ACHETER put 8.5 exp 2026-07-24 (crédit ~0.18$)",
      "score": 80.0,
      "summary": "CLF : bull put spread 9/8.5 exp 2026-07-24 (7j) — crédit 0.18$, risque max 0.32$, POP 71%, EV prudent +0.01$/action, gain max 56% du risque en 7j [ATTENTION : earnings avant l'expiration]",
      "details": {
        "strategie": "bull put spread",
        "jambes": [
          "VENDRE put 9",
          "ACHETER put 8.5"
        ],
        "expiry": "2026-07-24",
        "dte": 7,
        "credit_par_action": 0.18,
        "risque_max_par_action": 0.32,
        "prob_profit": 0.714,
        "esperance_gain_EV": 0.052,
        "edge_par_risque": 0.162,
        "ratio_gain_risque": 0.563,
        "rendement_annualise": 29.33,
        "kelly_pleine": 0.205,
        "demi_kelly_conseillee": 0.103,
        "spot": 9.31,
        "vol_estimee": 0.647,
        "iv_atm": 0.847,
        "ev_prudent_apres_frais": 0.014,
        "greeks": {
          "delta": 0.1897,
          "gamma": -0.1666,
          "theta_jour": 0.008,
          "vega": -0.0018
        },
        "attention_earnings": "résultats dans 6j, avant l'expiration — risque de gap"
      }
    },
    {
      "ticker": "RIOT",
      "kind": "strategie_optimale",
      "strategy": "VENDRE call 21 + ACHETER call 21.5 exp 2026-08-07 (crédit ~0.15$)",
      "score": 80.0,
      "summary": "RIOT : bear call spread 21/21.5 exp 2026-08-07 (21j) — crédit 0.15$, risque max 0.35$, POP 79%, EV prudent +0.01$/action, gain max 43% du risque en 21j [ATTENTION : earnings avant l'expiration]",
      "details": {
        "strategie": "bear call spread",
        "jambes": [
          "VENDRE call 21",
          "ACHETER call 21.5"
        ],
        "expiry": "2026-08-07",
        "dte": 21,
        "credit_par_action": 0.15,
        "risque_max_par_action": 0.35,
        "prob_profit": 0.793,
        "esperance_gain_EV": 0.048,
        "edge_par_risque": 0.138,
        "ratio_gain_risque": 0.429,
        "rendement_annualise": 7.449,
        "kelly_pleine": 0.309,
        "demi_kelly_conseillee": 0.155,
        "spot": 18.42,
        "vol_estimee": 0.802,
        "iv_atm": 0.972,
        "ev_prudent_apres_frais": 0.013,
        "greeks": {
          "delta": -0.0399,
          "gamma": -0.0071,
          "theta_jour": 0.0022,
          "vega": -0.0011
        },
        "attention_earnings": "résultats dans 13j, avant l'expiration — risque de gap"
      }
    },
    {
      "ticker": "PLTR",
      "kind": "put_cash_secured",
      "strategy": "Vendre put PLTR 127 exp 2026-08-07 @ ~6.55$ (capital requis 12,700$)",
      "score": 79.9,
      "summary": "PLTR : put 127 (21j, delta 0.37) rapporte ~88% annualisé, prob. de profit ~56%",
      "details": {
        "expiry": "2026-08-07",
        "dte": 21,
        "strike": 127.0,
        "mid": 6.55,
        "bid_vente": 6.4,
        "commission_incluse": 1.0,
        "delta": 0.37,
        "annual_yield": 0.875,
        "prob_profit": 0.56,
        "capital_requis": 12700,
        "greeks": {
          "delta": 0.3719,
          "gamma": -0.0173,
          "theta_jour": 0.1904
        }
      }
    },
    {
      "ticker": "SPY",
      "kind": "activite_inhabituelle",
      "strategy": "Surveiller / suivre le flux : call 744 exp 2026-07-22",
      "score": 79.4,
      "summary": "SPY : volume 1,634 vs OI 38 (x43.0) sur call 744 (-0.1% du spot), ~1.03M$ de prime — flux haussier",
      "details": {
        "expiry": "2026-07-22",
        "dte": 5,
        "side": "call",
        "strike": 744.0,
        "volume": 1634,
        "open_interest": 38,
        "ratio_vol_oi": 43.0,
        "premium_flow_usd": 1032688
      }
    },
    {
      "ticker": "SPY",
      "kind": "activite_inhabituelle",
      "strategy": "Surveiller / suivre le flux : call 743 exp 2026-07-22",
      "score": 79.4,
      "summary": "SPY : volume 2,224 vs OI 58 (x38.3) sur call 743 (-0.2% du spot), ~1.49M$ de prime — flux haussier",
      "details": {
        "expiry": "2026-07-22",
        "dte": 5,
        "side": "call",
        "strike": 743.0,
        "volume": 2224,
        "open_interest": 58,
        "ratio_vol_oi": 38.34,
        "premium_flow_usd": 1487856
      }
    },
    {
      "ticker": "QQQ",
      "kind": "activite_inhabituelle",
      "strategy": "Surveiller / suivre le flux : put 682 exp 2026-07-31",
      "score": 79.2,
      "summary": "QQQ : volume 9,547 vs OI 448 (x21.3) sur put 682 (-1.7% du spot), ~8.76M$ de prime — flux baissier (ou couverture)",
      "details": {
        "expiry": "2026-07-31",
        "dte": 14,
        "side": "put",
        "strike": 682.0,
        "volume": 9547,
        "open_interest": 448,
        "ratio_vol_oi": 21.31,
        "premium_flow_usd": 8764146
      }
    },
    {
      "ticker": "TLRY",
      "kind": "put_cash_secured",
      "strategy": "Vendre put TLRY 4 exp 2026-08-07 @ ~0.24$ (capital requis 400$)",
      "score": 78.2,
      "summary": "TLRY : put 4 (21j, delta 0.33) rapporte ~83% annualisé, prob. de profit ~59%",
      "details": {
        "expiry": "2026-08-07",
        "dte": 21,
        "strike": 4.0,
        "mid": 0.24,
        "bid_vente": 0.2,
        "commission_incluse": 1.0,
        "delta": 0.33,
        "annual_yield": 0.826,
        "prob_profit": 0.59,
        "capital_requis": 400,
        "greeks": {
          "delta": 0.3341,
          "gamma": -0.4061,
          "theta_jour": 0.0076
        }
      }
    },
    {
      "ticker": "COIN",
      "kind": "skew_inverse",
      "strategy": "Signal rare : spéculation haussière agressive — surveiller un squeeze / call spreads",
      "score": 78.1,
      "summary": "COIN : skew INVERSÉ, calls +5% à 87% plus chers que puts -5% à 79% (-8.3 pts) — demande haussière anormale",
      "details": {
        "expiry": "2026-08-07",
        "dte": 21,
        "put_iv": 0.7913,
        "call_iv": 0.874,
        "skew_pts": -8.3
      }
    },
    {
      "ticker": "AGNC",
      "kind": "earnings_iv",
      "strategy": "Jouer l'IV crush : iron condor / strangle vendu APRÈS l'annonce, ou calendar spread avant — éviter l'achat sec de calls/puts",
      "score": 77.9,
      "summary": "AGNC : résultats dans 3 j, IV gonflée à 26% (x1.40 vs réalisée) — l'IV va s'écraser après l'annonce",
      "details": {
        "earnings_days": 3,
        "iv_atm": 0.2598,
        "rv_20d": 0.1859,
        "iv_inflation": 1.4
      }
    },
    {
      "ticker": "META",
      "kind": "strategie_optimale",
      "strategy": "VENDRE call 700 + ACHETER call 705 exp 2026-08-07 (crédit ~1.30$)",
      "score": 76.8,
      "summary": "META : bear call spread 700/705 exp 2026-08-07 (21j) — crédit 1.30$, risque max 3.70$, POP 81%, EV prudent +0.20$/action, gain max 35% du risque en 21j [ATTENTION : earnings avant l'expiration]",
      "details": {
        "strategie": "bear call spread",
        "jambes": [
          "VENDRE call 700",
          "ACHETER call 705"
        ],
        "expiry": "2026-08-07",
        "dte": 21,
        "credit_par_action": 1.3,
        "risque_max_par_action": 3.7,
        "prob_profit": 0.811,
        "esperance_gain_EV": 0.349,
        "edge_par_risque": 0.094,
        "ratio_gain_risque": 0.351,
        "rendement_annualise": 6.107,
        "kelly_pleine": 0.273,
        "demi_kelly_conseillee": 0.137,
        "spot": 626.73,
        "vol_estimee": 0.577,
        "iv_atm": 0.591,
        "ev_prudent_apres_frais": 0.199,
        "greeks": {
          "delta": -0.0156,
          "gamma": -0.0001,
          "theta_jour": 0.0249,
          "vega": -0.0173
        },
        "attention_earnings": "résultats dans 12j, avant l'expiration — risque de gap"
      }
    },
    {
      "ticker": "RIVN",
      "kind": "put_cash_secured",
      "strategy": "Vendre put RIVN 16 exp 2026-08-07 @ ~0.83$ (capital requis 1,600$)",
      "score": 76.7,
      "summary": "RIVN : put 16 (21j, delta 0.34) rapporte ~80% annualisé, prob. de profit ~59%",
      "details": {
        "expiry": "2026-08-07",
        "dte": 21,
        "strike": 16.0,
        "mid": 0.83,
        "bid_vente": 0.75,
        "commission_incluse": 1.0,
        "delta": 0.34,
        "annual_yield": 0.804,
        "prob_profit": 0.59,
        "capital_requis": 1600,
        "greeks": {
          "delta": 0.3401,
          "gamma": -0.1163,
          "theta_jour": 0.0267
        }
      }
    },
    {
      "ticker": "LCID",
      "kind": "achat_call",
      "strategy": "ACHETER call 7.5 exp 2026-08-07 @ ~0.36$ (36$/contrat, perte max = la prime)",
      "score": 76.2,
      "summary": "LCID : 4/4 signaux hausse convergents (flux +44%, momentum +30.2%, RSI 58, skew +1.00) → call 7.5 (21j) @ 0.36$ — si mouvement 1σ (34.2%) : +305% sur la prime",
      "details": {
        "sens": "HAUSSE",
        "side": "call",
        "strike": 7.5,
        "expiry": "2026-08-07",
        "dte": 21,
        "prime_par_action": 0.36,
        "cout_par_contrat": 36,
        "delta": 0.36,
        "breakeven": 7.87,
        "mouvement_necessaire": 0.176,
        "mouvement_attendu_1sigma": 0.342,
        "gain_si_mouvement_1sigma": 3.05,
        "prob_profit_a_echeance": 0.26,
        "score_direction": 0.8,
        "signaux": {
          "direction": 0.8007428574210762,
          "flux": 0.44,
          "momentum_20j": 0.302,
          "rsi": 58.0,
          "breakout": 1.0,
          "skew": 1.0
        },
        "iv_contrat": 0.999,
        "vol_realisee": 1.475,
        "spot": 6.69,
        "attention_earnings": "résultats dans 18j, avant l'expiration : tu paies l'IV gonflée et elle s'écrasera après l'annonce (IV crush)"
      }
    },
    {
      "ticker": "SOFI",
      "kind": "put_cash_secured",
      "strategy": "Vendre put SOFI 16 exp 2026-08-07 @ ~0.74$ (capital requis 1,600$)",
      "score": 75.1,
      "summary": "SOFI : put 16 (21j, delta 0.34) rapporte ~78% annualisé, prob. de profit ~59%",
      "details": {
        "expiry": "2026-08-07",
        "dte": 21,
        "strike": 16.0,
        "mid": 0.74,
        "bid_vente": 0.73,
        "commission_incluse": 1.0,
        "delta": 0.34,
        "annual_yield": 0.782,
        "prob_profit": 0.59,
        "capital_requis": 1600,
        "greeks": {
          "delta": 0.3424,
          "gamma": -0.131,
          "theta_jour": 0.0237
        }
      }
    },
    {
      "ticker": "RIOT",
      "kind": "strategie_optimale",
      "strategy": "VENDRE put 16 + ACHETER put 15 exp 2026-08-07 (crédit ~0.28$)",
      "score": 73.9,
      "summary": "RIOT : bull put spread 16/15 exp 2026-08-07 (21j) — crédit 0.28$, risque max 0.72$, POP 77%, EV prudent +0.02$/action, gain max 39% du risque en 21j [ATTENTION : earnings avant l'expiration]",
      "details": {
        "strategie": "bull put spread",
        "jambes": [
          "VENDRE put 16",
          "ACHETER put 15"
        ],
        "expiry": "2026-08-07",
        "dte": 21,
        "credit_par_action": 0.28,
        "risque_max_par_action": 0.72,
        "prob_profit": 0.766,
        "esperance_gain_EV": 0.072,
        "edge_par_risque": 0.1,
        "ratio_gain_risque": 0.389,
        "rendement_annualise": 6.759,
        "kelly_pleine": 0.165,
        "demi_kelly_conseillee": 0.083,
        "spot": 18.42,
        "vol_estimee": 0.802,
        "iv_atm": 0.972,
        "ev_prudent_apres_frais": 0.024,
        "greeks": {
          "delta": 0.0805,
          "gamma": -0.0227,
          "theta_jour": 0.0066,
          "vega": -0.0036
        },
        "attention_earnings": "résultats dans 13j, avant l'expiration — risque de gap"
      }
    },
    {
      "ticker": "SOFI",
      "kind": "strategie_optimale",
      "strategy": "VENDRE put 15 + ACHETER put 14 exp 2026-08-07 (crédit ~0.21$)",
      "score": 73.2,
      "summary": "SOFI : bull put spread 15/14 exp 2026-08-07 (21j) — crédit 0.21$, risque max 0.79$, POP 82%, EV prudent +0.03$/action, gain max 27% du risque en 21j [ATTENTION : earnings avant l'expiration]",
      "details": {
        "strategie": "bull put spread",
        "jambes": [
          "VENDRE put 15",
          "ACHETER put 14"
        ],
        "expiry": "2026-08-07",
        "dte": 21,
        "credit_par_action": 0.21,
        "risque_max_par_action": 0.79,
        "prob_profit": 0.818,
        "esperance_gain_EV": 0.067,
        "edge_par_risque": 0.085,
        "ratio_gain_risque": 0.266,
        "rendement_annualise": 4.62,
        "kelly_pleine": 0.134,
        "demi_kelly_conseillee": 0.067,
        "spot": 16.84,
        "vol_estimee": 0.555,
        "iv_atm": 0.707,
        "ev_prudent_apres_frais": 0.026,
        "greeks": {
          "delta": 0.0994,
          "gamma": -0.0527,
          "theta_jour": 0.0061,
          "vega": -0.0048
        },
        "attention_earnings": "résultats dans 12j, avant l'expiration — risque de gap"
      }
    },
    {
      "ticker": "CLF",
      "kind": "earnings_iv",
      "strategy": "Jouer l'IV crush : iron condor / strangle vendu APRÈS l'annonce, ou calendar spread avant — éviter l'achat sec de calls/puts",
      "score": 72.2,
      "summary": "CLF : résultats dans 6 j, IV gonflée à 85% (x1.65 vs réalisée) — l'IV va s'écraser après l'annonce",
      "details": {
        "earnings_days": 6,
        "iv_atm": 0.8467,
        "rv_20d": 0.5133,
        "iv_inflation": 1.65
      }
    },
    {
      "ticker": "CLF",
      "kind": "put_cash_secured",
      "strategy": "Vendre put CLF 8.5 exp 2026-08-07 @ ~0.41$ (capital requis 850$)",
      "score": 72.0,
      "summary": "CLF : put 8.5 (21j, delta 0.29) rapporte ~70% annualisé, prob. de profit ~64%",
      "details": {
        "expiry": "2026-08-07",
        "dte": 21,
        "strike": 8.5,
        "mid": 0.41,
        "bid_vente": 0.35,
        "commission_incluse": 1.0,
        "delta": 0.29,
        "annual_yield": 0.695,
        "prob_profit": 0.64,
        "capital_requis": 850,
        "greeks": {
          "delta": 0.287,
          "gamma": -0.1786,
          "theta_jour": 0.0151
        }
      }
    },
    {
      "ticker": "SNAP",
      "kind": "put_cash_secured",
      "strategy": "Vendre put SNAP 4 exp 2026-08-07 @ ~0.17$ (capital requis 400$)",
      "score": 71.4,
      "summary": "SNAP : put 4 (21j, delta 0.25) rapporte ~65% annualisé, prob. de profit ~68%",
      "details": {
        "expiry": "2026-08-07",
        "dte": 21,
        "strike": 4.0,
        "mid": 0.17,
        "bid_vente": 0.16,
        "commission_incluse": 1.0,
        "delta": 0.25,
        "annual_yield": 0.652,
        "prob_profit": 0.68,
        "capital_requis": 400,
        "greeks": {
          "delta": 0.2452,
          "gamma": -0.329,
          "theta_jour": 0.007
        }
      }
    },
    {
      "ticker": "COIN",
      "kind": "activite_inhabituelle",
      "strategy": "Surveiller / suivre le flux : call 172.5 exp 2026-07-24",
      "score": 71.0,
      "summary": "COIN : volume 6,027 vs OI 278 (x21.7) sur call 172.5 (+10.5% du spot), ~1.18M$ de prime — flux haussier",
      "details": {
        "expiry": "2026-07-24",
        "dte": 7,
        "side": "call",
        "strike": 172.5,
        "volume": 6027,
        "open_interest": 278,
        "ratio_vol_oi": 21.68,
        "premium_flow_usd": 1175265
      }
    },
    {
      "ticker": "PLUG",
      "kind": "skew_inverse",
      "strategy": "Signal rare : spéculation haussière agressive — surveiller un squeeze / call spreads",
      "score": 70.0,
      "summary": "PLUG : skew INVERSÉ, calls +5% à 102% plus chers que puts -5% à 95% (-6.3 pts) — demande haussière anormale",
      "details": {
        "expiry": "2026-08-07",
        "dte": 21,
        "put_iv": 0.9531,
        "call_iv": 1.0156,
        "skew_pts": -6.3
      }
    },
    {
      "ticker": "META",
      "kind": "strategie_optimale",
      "strategy": "VENDRE call 715 + ACHETER call 720 exp 2026-08-07 (crédit ~1.03$)",
      "score": 70.0,
      "summary": "META : bear call spread 715/720 exp 2026-08-07 (21j) — crédit 1.03$, risque max 3.97$, POP 85%, EV prudent +0.14$/action, gain max 26% du risque en 21j [ATTENTION : earnings avant l'expiration]",
      "details": {
        "strategie": "bear call spread",
        "jambes": [
          "VENDRE call 715",
          "ACHETER call 720"
        ],
        "expiry": "2026-08-07",
        "dte": 21,
        "credit_par_action": 1.03,
        "risque_max_par_action": 3.97,
        "prob_profit": 0.849,
        "esperance_gain_EV": 0.267,
        "edge_par_risque": 0.067,
        "ratio_gain_risque": 0.258,
        "rendement_annualise": 4.482,
        "kelly_pleine": 0.263,
        "demi_kelly_conseillee": 0.132,
        "spot": 626.73,
        "vol_estimee": 0.577,
        "iv_atm": 0.591,
        "ev_prudent_apres_frais": 0.145,
        "greeks": {
          "delta": -0.0135,
          "gamma": -0.0001,
          "theta_jour": 0.0258,
          "vega": -0.0181
        },
        "attention_earnings": "résultats dans 12j, avant l'expiration — risque de gap"
      }
    },
    {
      "ticker": "SPY",
      "kind": "activite_inhabituelle",
      "strategy": "Surveiller / suivre le flux : put 716 exp 2026-07-31",
      "score": 69.9,
      "summary": "SPY : volume 16,131 vs OI 1,123 (x14.4) sur put 716 (-3.8% du spot), ~3.27M$ de prime — flux baissier (ou couverture)",
      "details": {
        "expiry": "2026-07-31",
        "dte": 14,
        "side": "put",
        "strike": 716.0,
        "volume": 16131,
        "open_interest": 1123,
        "ratio_vol_oi": 14.36,
        "premium_flow_usd": 3274592
      }
    },
    {
      "ticker": "PLUG",
      "kind": "put_cash_secured",
      "strategy": "Vendre put PLUG 2 exp 2026-08-28 @ ~0.20$ (capital requis 200$)",
      "score": 69.1,
      "summary": "PLUG : put 2 (42j, delta 0.33) rapporte ~74% annualisé, prob. de profit ~54%",
      "details": {
        "expiry": "2026-08-28",
        "dte": 42,
        "strike": 2.0,
        "mid": 0.2,
        "bid_vente": 0.18,
        "commission_incluse": 1.0,
        "delta": 0.33,
        "annual_yield": 0.739,
        "prob_profit": 0.54,
        "capital_requis": 200,
        "greeks": {
          "delta": 0.3313,
          "gamma": -0.5116,
          "theta_jour": 0.0029
        }
      }
    },
    {
      "ticker": "CLF",
      "kind": "strategie_optimale",
      "strategy": "VENDRE call 11 + ACHETER call 12 exp 2026-08-07 (crédit ~0.15$)",
      "score": 68.8,
      "summary": "CLF : bear call spread 11/12 exp 2026-08-07 (21j) — crédit 0.15$, risque max 0.85$, POP 89%, EV prudent +0.03$/action, gain max 17% du risque en 21j [ATTENTION : earnings avant l'expiration]",
      "details": {
        "strategie": "bear call spread",
        "jambes": [
          "VENDRE call 11",
          "ACHETER call 12"
        ],
        "expiry": "2026-08-07",
        "dte": 21,
        "credit_par_action": 0.15,
        "risque_max_par_action": 0.85,
        "prob_profit": 0.891,
        "esperance_gain_EV": 0.064,
        "edge_par_risque": 0.075,
        "ratio_gain_risque": 0.17,
        "rendement_annualise": 2.948,
        "kelly_pleine": 0.251,
        "demi_kelly_conseillee": 0.126,
        "spot": 9.31,
        "vol_estimee": 0.647,
        "iv_atm": 0.847,
        "ev_prudent_apres_frais": 0.03,
        "greeks": {
          "delta": -0.1022,
          "gamma": -0.0867,
          "theta_jour": 0.0044,
          "vega": -0.0028
        },
        "attention_earnings": "résultats dans 6j, avant l'expiration — risque de gap"
      }
    },
    {
      "ticker": "T",
      "kind": "strategie_optimale",
      "strategy": "VENDRE put 21 + ACHETER put 20 + VENDRE call 23 + ACHETER call 23.5 exp 2026-07-24 (crédit ~0.23$)",
      "score": 68.6,
      "summary": "T : iron condor 21/20/23/23.5 exp 2026-07-24 (7j) — crédit 0.23$, risque max 0.77$, POP 73%, EV prudent +0.03$/action, gain max 29% du risque en 7j [ATTENTION : earnings avant l'expiration]",
      "details": {
        "strategie": "iron condor",
        "jambes": [
          "VENDRE put 21",
          "ACHETER put 20",
          "VENDRE call 23",
          "ACHETER call 23.5"
        ],
        "expiry": "2026-07-24",
        "dte": 7,
        "credit_par_action": 0.23,
        "risque_max_par_action": 0.77,
        "prob_profit": 0.726,
        "esperance_gain_EV": 0.076,
        "edge_par_risque": 0.098,
        "ratio_gain_risque": 0.29,
        "rendement_annualise": 15.138,
        "kelly_pleine": 0.0,
        "demi_kelly_conseillee": 0.0,
        "spot": 22.28,
        "vol_estimee": 0.355,
        "iv_atm": 0.375,
        "ev_prudent_apres_frais": 0.034,
        "greeks": {
          "delta": -0.03,
          "gamma": -0.2294,
          "theta_jour": 0.0198,
          "vega": -0.0078
        },
        "attention_earnings": "résultats dans 5j, avant l'expiration — risque de gap"
      }
    },
    {
      "ticker": "PLUG",
      "kind": "prime_riche",
      "strategy": "Vente de prime : put cash-secured, covered call ou iron condor",
      "score": 68.4,
      "summary": "PLUG : IV 106% vs vol réalisée 56% (ratio x1.91) — les options sont chères, avantage au vendeur",
      "details": {
        "iv_atm": 1.0586,
        "rv_20d": 0.5551,
        "ratio": 1.91
      }
    },
    {
      "ticker": "PBR",
      "kind": "prime_riche",
      "strategy": "Vente de prime : put cash-secured, covered call ou iron condor",
      "score": 67.3,
      "summary": "PBR : IV 53% vs vol réalisée 28% (ratio x1.89) — les options sont chères, avantage au vendeur",
      "details": {
        "iv_atm": 0.5259,
        "rv_20d": 0.2784,
        "ratio": 1.89
      }
    },
    {
      "ticker": "AMD",
      "kind": "skew_inverse",
      "strategy": "Signal rare : spéculation haussière agressive — surveiller un squeeze / call spreads",
      "score": 67.1,
      "summary": "AMD : skew INVERSÉ, calls +5% à 84% plus chers que puts -5% à 79% (-5.5 pts) — demande haussière anormale",
      "details": {
        "expiry": "2026-08-28",
        "dte": 42,
        "put_iv": 0.7893,
        "call_iv": 0.8446,
        "skew_pts": -5.5
      }
    },
    {
      "ticker": "F",
      "kind": "prime_riche",
      "strategy": "Vente de prime : put cash-secured, covered call ou iron condor",
      "score": 67.0,
      "summary": "F : IV 46% vs vol réalisée 24% (ratio x1.88) — les options sont chères, avantage au vendeur",
      "details": {
        "iv_atm": 0.4614,
        "rv_20d": 0.2449,
        "ratio": 1.88
      }
    },
    {
      "ticker": "INTC",
      "kind": "activite_inhabituelle",
      "strategy": "Surveiller / suivre le flux : call 95 exp 2026-07-22",
      "score": 66.0,
      "summary": "INTC : volume 7,036 vs OI 602 (x11.7) sur call 95 (+2.1% du spot), ~2.46M$ de prime — flux haussier",
      "details": {
        "expiry": "2026-07-22",
        "dte": 5,
        "side": "call",
        "strike": 95.0,
        "volume": 7036,
        "open_interest": 602,
        "ratio_vol_oi": 11.69,
        "premium_flow_usd": 2462600
      }
    },
    {
      "ticker": "META",
      "kind": "put_cash_secured",
      "strategy": "Vendre put META 605 exp 2026-08-07 @ ~21.90$ (capital requis 60,500$)",
      "score": 63.5,
      "summary": "META : put 605 (21j, delta 0.36) rapporte ~62% annualisé, prob. de profit ~59%",
      "details": {
        "expiry": "2026-08-07",
        "dte": 21,
        "strike": 605.0,
        "mid": 21.9,
        "bid_vente": 21.45,
        "commission_incluse": 1.0,
        "delta": 0.36,
        "annual_yield": 0.616,
        "prob_profit": 0.59,
        "capital_requis": 60500,
        "greeks": {
          "delta": 0.3577,
          "gamma": -0.0047,
          "theta_jour": 0.6684
        }
      }
    },
    {
      "ticker": "COIN",
      "kind": "activite_inhabituelle",
      "strategy": "Surveiller / suivre le flux : call 160 exp 2026-07-24",
      "score": 63.5,
      "summary": "COIN : volume 5,448 vs OI 593 (x9.2) sur call 160 (+2.5% du spot), ~2.85M$ de prime — flux haussier",
      "details": {
        "expiry": "2026-07-24",
        "dte": 7,
        "side": "call",
        "strike": 160.0,
        "volume": 5448,
        "open_interest": 593,
        "ratio_vol_oi": 9.19,
        "premium_flow_usd": 2854752
      }
    },
    {
      "ticker": "PBR",
      "kind": "achat_call",
      "strategy": "ACHETER call 18.5 exp 2026-08-07 @ ~0.40$ (39$/contrat, perte max = la prime)",
      "score": 63.4,
      "summary": "PBR : 4/4 signaux hausse convergents (flux +44%, momentum +6.0%, RSI 55, skew +1.00) → call 18.5 (21j) @ 0.40$ — si mouvement 1σ (9.1%) : +128% sur la prime",
      "details": {
        "sens": "HAUSSE",
        "side": "call",
        "strike": 18.5,
        "expiry": "2026-08-07",
        "dte": 21,
        "prime_par_action": 0.4,
        "cout_par_contrat": 39,
        "delta": 0.43,
        "breakeven": 18.89,
        "mouvement_necessaire": 0.062,
        "mouvement_attendu_1sigma": 0.091,
        "gain_si_mouvement_1sigma": 1.28,
        "prob_profit_a_echeance": 0.24,
        "score_direction": 0.64,
        "signaux": {
          "direction": 0.6369515557580558,
          "flux": 0.44,
          "momentum_20j": 0.06,
          "rsi": 55.0,
          "breakout": 0.87,
          "skew": 1.0
        },
        "iv_contrat": 0.603,
        "vol_realisee": 0.278,
        "spot": 17.79,
        "attention_earnings": "résultats dans 20j, avant l'expiration : tu paies l'IV gonflée et elle s'écrasera après l'annonce (IV crush)"
      }
    },
    {
      "ticker": "QQQ",
      "kind": "activite_inhabituelle",
      "strategy": "Surveiller / suivre le flux : put 685 exp 2026-07-31",
      "score": 63.2,
      "summary": "QQQ : volume 18,106 vs OI 3,800 (x4.8) sur put 685 (-1.3% du spot), ~19.46M$ de prime — flux baissier (ou couverture)",
      "details": {
        "expiry": "2026-07-31",
        "dte": 14,
        "side": "put",
        "strike": 685.0,
        "volume": 18106,
        "open_interest": 3800,
        "ratio_vol_oi": 4.76,
        "premium_flow_usd": 19463950
      }
    },
    {
      "ticker": "PFE",
      "kind": "achat_call",
      "strategy": "ACHETER call 26 exp 2026-08-07 @ ~0.23$ (23$/contrat, perte max = la prime)",
      "score": 63.2,
      "summary": "PFE : 3/4 signaux hausse convergents (flux +79%, momentum -2.2%, RSI 57, skew +1.00) → call 26 (21j) @ 0.23$ — si mouvement 1σ (6.3%) : +298% sur la prime",
      "details": {
        "sens": "HAUSSE",
        "side": "call",
        "strike": 26.0,
        "expiry": "2026-08-07",
        "dte": 21,
        "prime_par_action": 0.23,
        "cout_par_contrat": 23,
        "delta": 0.33,
        "breakeven": 26.23,
        "mouvement_necessaire": 0.035,
        "mouvement_attendu_1sigma": 0.063,
        "gain_si_mouvement_1sigma": 2.98,
        "prob_profit_a_echeance": 0.28,
        "score_direction": 0.63,
        "signaux": {
          "direction": 0.6312998285990332,
          "flux": 0.79,
          "momentum_20j": -0.022,
          "rsi": 57.0,
          "breakout": 1.0,
          "skew": 1.0
        },
        "iv_contrat": 0.204,
        "vol_realisee": 0.262,
        "spot": 25.34,
        "attention_earnings": "résultats dans 18j, avant l'expiration : tu paies l'IV gonflée et elle s'écrasera après l'annonce (IV crush)"
      }
    },
    {
      "ticker": "T",
      "kind": "earnings_iv",
      "strategy": "Jouer l'IV crush : iron condor / strangle vendu APRÈS l'annonce, ou calendar spread avant — éviter l'achat sec de calls/puts",
      "score": 62.3,
      "summary": "T : résultats dans 5 j, IV gonflée à 37% (x1.09 vs réalisée) — l'IV va s'écraser après l'annonce",
      "details": {
        "earnings_days": 5,
        "iv_atm": 0.3745,
        "rv_20d": 0.3425,
        "iv_inflation": 1.09
      }
    },
    {
      "ticker": "NVDA",
      "kind": "put_cash_secured",
      "strategy": "Vendre put NVDA 197.5 exp 2026-07-31 @ ~4.35$ (capital requis 19,750$)",
      "score": 61.8,
      "summary": "NVDA : put 197.5 (14j, delta 0.35) rapporte ~57% annualisé, prob. de profit ~62%",
      "details": {
        "expiry": "2026-07-31",
        "dte": 14,
        "strike": 197.5,
        "mid": 4.35,
        "bid_vente": 4.3,
        "commission_incluse": 1.0,
        "delta": 0.35,
        "annual_yield": 0.566,
        "prob_profit": 0.62,
        "capital_requis": 19750,
        "greeks": {
          "delta": 0.3481,
          "gamma": -0.0223,
          "theta_jour": 0.2098
        }
      }
    },
    {
      "ticker": "F",
      "kind": "strategie_optimale",
      "strategy": "VENDRE put 13.5 + ACHETER put 12 exp 2026-08-07 (crédit ~0.22$)",
      "score": 61.7,
      "summary": "F : bull put spread 13.5/12 exp 2026-08-07 (21j) — crédit 0.22$, risque max 1.28$, POP 82%, EV prudent +0.04$/action, gain max 17% du risque en 21j [ATTENTION : earnings avant l'expiration]",
      "details": {
        "strategie": "bull put spread",
        "jambes": [
          "VENDRE put 13.5",
          "ACHETER put 12"
        ],
        "expiry": "2026-08-07",
        "dte": 21,
        "credit_par_action": 0.22,
        "risque_max_par_action": 1.28,
        "prob_profit": 0.818,
        "esperance_gain_EV": 0.086,
        "edge_par_risque": 0.067,
        "ratio_gain_risque": 0.172,
        "rendement_annualise": 2.987,
        "kelly_pleine": 0.0,
        "demi_kelly_conseillee": 0.0,
        "spot": 14.32,
        "vol_estimee": 0.332,
        "iv_atm": 0.461,
        "ev_prudent_apres_frais": 0.044,
        "greeks": {
          "delta": 0.197,
          "gamma": -0.2264,
          "theta_jour": 0.0066,
          "vega": -0.0089
        },
        "attention_earnings": "résultats dans 11j, avant l'expiration — risque de gap"
      }
    },
    {
      "ticker": "TSLA",
      "kind": "put_cash_secured",
      "strategy": "Vendre put TSLA 365 exp 2026-08-07 @ ~12.00$ (capital requis 36,500$)",
      "score": 61.2,
      "summary": "TSLA : put 365 (21j, delta 0.34) rapporte ~57% annualisé, prob. de profit ~61%",
      "details": {
        "expiry": "2026-08-07",
        "dte": 21,
        "strike": 365.0,
        "mid": 12.0,
        "bid_vente": 11.9,
        "commission_incluse": 1.0,
        "delta": 0.34,
        "annual_yield": 0.566,
        "prob_profit": 0.61,
        "capital_requis": 36500,
        "greeks": {
          "delta": 0.3401,
          "gamma": -0.0079,
          "theta_jour": 0.3876
        }
      }
    },
    {
      "ticker": "AAL",
      "kind": "put_cash_secured",
      "strategy": "Vendre put AAL 14.5 exp 2026-08-07 @ ~0.51$ (capital requis 1,450$)",
      "score": 61.0,
      "summary": "AAL : put 14.5 (21j, delta 0.34) rapporte ~56% annualisé, prob. de profit ~61%",
      "details": {
        "expiry": "2026-08-07",
        "dte": 21,
        "strike": 14.5,
        "mid": 0.51,
        "bid_vente": 0.48,
        "commission_incluse": 1.0,
        "delta": 0.34,
        "annual_yield": 0.563,
        "prob_profit": 0.61,
        "capital_requis": 1450,
        "greeks": {
          "delta": 0.3415,
          "gamma": -0.1895,
          "theta_jour": 0.0162
        }
      }
    },
    {
      "ticker": "RIVN",
      "kind": "skew_inverse",
      "strategy": "Signal rare : spéculation haussière agressive — surveiller un squeeze / call spreads",
      "score": 60.6,
      "summary": "RIVN : skew INVERSÉ, calls +5% à 81% plus chers que puts -5% à 78% (-3.9 pts) — demande haussière anormale",
      "details": {
        "expiry": "2026-08-07",
        "dte": 21,
        "put_iv": 0.7754,
        "call_iv": 0.8145,
        "skew_pts": -3.9
      }
    },
    {
      "ticker": "AAL",
      "kind": "earnings_iv",
      "strategy": "Jouer l'IV crush : iron condor / strangle vendu APRÈS l'annonce, ou calendar spread avant — éviter l'achat sec de calls/puts",
      "score": 60.4,
      "summary": "AAL : résultats dans 6 j, IV gonflée à 54% (x1.17 vs réalisée) — l'IV va s'écraser après l'annonce",
      "details": {
        "earnings_days": 6,
        "iv_atm": 0.5381,
        "rv_20d": 0.4581,
        "iv_inflation": 1.17
      }
    },
    {
      "ticker": "BAC",
      "kind": "activite_inhabituelle",
      "strategy": "Surveiller / suivre le flux : call 55 exp 2026-08-07",
      "score": 60.2,
      "summary": "BAC : volume 1,006 vs OI 92 (x10.9) sur call 55 (-11.1% du spot), ~0.72M$ de prime — flux haussier",
      "details": {
        "expiry": "2026-08-07",
        "dte": 21,
        "side": "call",
        "strike": 55.0,
        "volume": 1006,
        "open_interest": 92,
        "ratio_vol_oi": 10.93,
        "premium_flow_usd": 715266
      }
    },
    {
      "ticker": "TSLA",
      "kind": "earnings_iv",
      "strategy": "Jouer l'IV crush : iron condor / strangle vendu APRÈS l'annonce, ou calendar spread avant — éviter l'achat sec de calls/puts",
      "score": 60,
      "summary": "TSLA : résultats dans 5 j, IV gonflée à 51% (x0.86 vs réalisée) — l'IV va s'écraser après l'annonce",
      "details": {
        "earnings_days": 5,
        "iv_atm": 0.5091,
        "rv_20d": 0.5946,
        "iv_inflation": 0.86
      }
    },
    {
      "ticker": "QQQ",
      "kind": "activite_inhabituelle",
      "strategy": "Surveiller / suivre le flux : call 690 exp 2026-07-22",
      "score": 59.5,
      "summary": "QQQ : volume 657 vs OI 67 (x9.8) sur call 690 (-0.5% du spot), ~0.87M$ de prime — flux haussier",
      "details": {
        "expiry": "2026-07-22",
        "dte": 5,
        "side": "call",
        "strike": 690.0,
        "volume": 657,
        "open_interest": 67,
        "ratio_vol_oi": 9.81,
        "premium_flow_usd": 869211
      }
    },
    {
      "ticker": "NIO",
      "kind": "skew_inverse",
      "strategy": "Signal rare : spéculation haussière agressive — surveiller un squeeze / call spreads",
      "score": 59.1,
      "summary": "NIO : skew INVERSÉ, calls +5% à 57% plus chers que puts -5% à 54% (-3.5 pts) — demande haussière anormale",
      "details": {
        "expiry": "2026-08-07",
        "dte": 21,
        "put_iv": 0.5352,
        "call_iv": 0.5703,
        "skew_pts": -3.5
      }
    },
    {
      "ticker": "T",
      "kind": "achat_call",
      "strategy": "ACHETER call 23 exp 2026-08-07 @ ~0.47$ (47$/contrat, perte max = la prime)",
      "score": 58.3,
      "summary": "T : 3/4 signaux hausse convergents (flux +91%, momentum +0.6%, RSI 55, skew +0.30) → call 23 (21j) @ 0.47$ — si mouvement 1σ (8.5%) : +148% sur la prime",
      "details": {
        "sens": "HAUSSE",
        "side": "call",
        "strike": 23.0,
        "expiry": "2026-08-07",
        "dte": 21,
        "prime_par_action": 0.47,
        "cout_par_contrat": 47,
        "delta": 0.39,
        "breakeven": 23.48,
        "mouvement_necessaire": 0.054,
        "mouvement_attendu_1sigma": 0.085,
        "gain_si_mouvement_1sigma": 1.48,
        "prob_profit_a_echeance": 0.26,
        "score_direction": 0.55,
        "signaux": {
          "direction": 0.5516317260237491,
          "flux": 0.91,
          "momentum_20j": 0.006,
          "rsi": 55.0,
          "breakout": 0.8,
          "skew": 0.3
        },
        "iv_contrat": 0.369,
        "vol_realisee": 0.342,
        "spot": 22.28,
        "attention_earnings": "résultats dans 5j, avant l'expiration : tu paies l'IV gonflée et elle s'écrasera après l'annonce (IV crush)"
      }
    },
    {
      "ticker": "BAC",
      "kind": "achat_call",
      "strategy": "ACHETER call 63 exp 2026-08-07 @ ~0.81$ (81$/contrat, perte max = la prime)",
      "score": 57.7,
      "summary": "BAC : 3/4 signaux hausse convergents (flux +20%, momentum +9.4%, RSI 73, skew -0.16) → call 63 (21j) @ 0.81$ — si mouvement 1σ (5.0%) : +138% sur la prime",
      "details": {
        "sens": "HAUSSE",
        "side": "call",
        "strike": 63.0,
        "expiry": "2026-08-07",
        "dte": 21,
        "prime_par_action": 0.81,
        "cout_par_contrat": 81,
        "delta": 0.39,
        "breakeven": 63.81,
        "mouvement_necessaire": 0.032,
        "mouvement_attendu_1sigma": 0.05,
        "gain_si_mouvement_1sigma": 1.38,
        "prob_profit_a_echeance": 0.26,
        "score_direction": 0.4,
        "signaux": {
          "direction": 0.3959480623779131,
          "flux": 0.2,
          "momentum_20j": 0.094,
          "rsi": 73.0,
          "breakout": 1.0,
          "skew": -0.16
        },
        "iv_contrat": 0.216,
        "vol_realisee": 0.204,
        "spot": 61.83
      }
    },
    {
      "ticker": "INTC",
      "kind": "earnings_iv",
      "strategy": "Jouer l'IV crush : iron condor / strangle vendu APRÈS l'annonce, ou calendar spread avant — éviter l'achat sec de calls/puts",
      "score": 57.7,
      "summary": "INTC : résultats dans 6 j, IV gonflée à 92% (x1.07 vs réalisée) — l'IV va s'écraser après l'annonce",
      "details": {
        "earnings_days": 6,
        "iv_atm": 0.9151,
        "rv_20d": 0.8581,
        "iv_inflation": 1.07
      }
    },
    {
      "ticker": "TSLA",
      "kind": "activite_inhabituelle",
      "strategy": "Surveiller / suivre le flux : call 387.5 exp 2026-07-24",
      "score": 56.3,
      "summary": "TSLA : volume 2,556 vs OI 479 (x5.3) sur call 387.5 (+2.0% du spot), ~2.77M$ de prime — flux haussier",
      "details": {
        "expiry": "2026-07-24",
        "dte": 7,
        "side": "call",
        "strike": 387.5,
        "volume": 2556,
        "open_interest": 479,
        "ratio_vol_oi": 5.34,
        "premium_flow_usd": 2773260
      }
    },
    {
      "ticker": "AGNC",
      "kind": "achat_call",
      "strategy": "ACHETER call 11.5 exp 2026-08-07 @ ~0.13$ (13$/contrat, perte max = la prime)",
      "score": 55.6,
      "summary": "AGNC : 3/4 signaux hausse convergents (flux -3%, momentum +10.6%, RSI 63, skew +1.00) → call 11.5 (21j) @ 0.13$ — si mouvement 1σ (5.2%) : +167% sur la prime",
      "details": {
        "sens": "HAUSSE",
        "side": "call",
        "strike": 11.5,
        "expiry": "2026-08-07",
        "dte": 21,
        "prime_par_action": 0.13,
        "cout_par_contrat": 13,
        "delta": 0.37,
        "breakeven": 11.63,
        "mouvement_necessaire": 0.032,
        "mouvement_attendu_1sigma": 0.052,
        "gain_si_mouvement_1sigma": 1.67,
        "prob_profit_a_echeance": 0.26,
        "score_direction": 0.51,
        "signaux": {
          "direction": 0.5064456312445142,
          "flux": -0.03,
          "momentum_20j": 0.106,
          "rsi": 63.0,
          "breakout": 0.72,
          "skew": 1.0
        },
        "iv_contrat": 0.215,
        "vol_realisee": 0.186,
        "spot": 11.27,
        "attention_earnings": "résultats dans 3j, avant l'expiration : tu paies l'IV gonflée et elle s'écrasera après l'annonce (IV crush)"
      }
    },
    {
      "ticker": "COIN",
      "kind": "activite_inhabituelle",
      "strategy": "Surveiller / suivre le flux : call 165 exp 2026-07-24",
      "score": 54.4,
      "summary": "COIN : volume 6,296 vs OI 1,272 (x4.9) sur call 165 (+5.7% du spot), ~2.22M$ de prime — flux haussier",
      "details": {
        "expiry": "2026-07-24",
        "dte": 7,
        "side": "call",
        "strike": 165.0,
        "volume": 6296,
        "open_interest": 1272,
        "ratio_vol_oi": 4.95,
        "premium_flow_usd": 2216192
      }
    },
    {
      "ticker": "AAPL",
      "kind": "put_cash_secured",
      "strategy": "Vendre put AAPL 325 exp 2026-07-31 @ ~5.50$ (capital requis 32,500$)",
      "score": 53.4,
      "summary": "AAPL : put 325 (14j, delta 0.34) rapporte ~43% annualisé, prob. de profit ~64%",
      "details": {
        "expiry": "2026-07-31",
        "dte": 14,
        "strike": 325.0,
        "mid": 5.5,
        "bid_vente": 5.35,
        "commission_incluse": 1.0,
        "delta": 0.34,
        "annual_yield": 0.428,
        "prob_profit": 0.64,
        "capital_requis": 32500,
        "greeks": {
          "delta": 0.3374,
          "gamma": -0.0165,
          "theta_jour": 0.2751
        }
      }
    },
    {
      "ticker": "CCL",
      "kind": "put_cash_secured",
      "strategy": "Vendre put CCL 25 exp 2026-08-07 @ ~0.62$ (capital requis 2,500$)",
      "score": 53.3,
      "summary": "CCL : put 25 (21j, delta 0.29) rapporte ~41% annualisé, prob. de profit ~66%",
      "details": {
        "expiry": "2026-08-07",
        "dte": 21,
        "strike": 25.0,
        "mid": 0.62,
        "bid_vente": 0.6,
        "commission_incluse": 1.0,
        "delta": 0.29,
        "annual_yield": 0.41,
        "prob_profit": 0.66,
        "capital_requis": 2500,
        "greeks": {
          "delta": 0.2949,
          "gamma": -0.1148,
          "theta_jour": 0.0237
        }
      }
    },
    {
      "ticker": "TSLA",
      "kind": "activite_inhabituelle",
      "strategy": "Surveiller / suivre le flux : call 382.5 exp 2026-07-24",
      "score": 53.2,
      "summary": "TSLA : volume 900 vs OI 164 (x5.5) sur call 382.5 (+0.7% du spot), ~1.19M$ de prime — flux haussier",
      "details": {
        "expiry": "2026-07-24",
        "dte": 7,
        "side": "call",
        "strike": 382.5,
        "volume": 900,
        "open_interest": 164,
        "ratio_vol_oi": 5.49,
        "premium_flow_usd": 1192500
      }
    },
    {
      "ticker": "CLF",
      "kind": "prime_riche",
      "strategy": "Vente de prime : put cash-secured, covered call ou iron condor",
      "score": 53.0,
      "summary": "CLF : IV 85% vs vol réalisée 51% (ratio x1.65) — les options sont chères, avantage au vendeur",
      "details": {
        "iv_atm": 0.8467,
        "rv_20d": 0.5133,
        "ratio": 1.65
      }
    },
    {
      "ticker": "VALE",
      "kind": "achat_put",
      "strategy": "ACHETER put 14 exp 2026-08-07 @ ~0.23$ (22$/contrat, perte max = la prime)",
      "score": 52.6,
      "summary": "VALE : 3/4 signaux baisse convergents (flux +57%, momentum -8.8%, RSI 38, skew -1.00) → put 14 (21j) @ 0.23$ — si mouvement 1σ (8.7%) : +371% sur la prime",
      "details": {
        "sens": "BAISSE",
        "side": "put",
        "strike": 14.0,
        "expiry": "2026-08-07",
        "dte": 21,
        "prime_par_action": 0.23,
        "cout_par_contrat": 22,
        "delta": 0.42,
        "breakeven": 13.78,
        "mouvement_necessaire": -0.028,
        "mouvement_attendu_1sigma": -0.087,
        "gain_si_mouvement_1sigma": 3.71,
        "prob_profit_a_echeance": 0.39,
        "score_direction": -0.32,
        "signaux": {
          "direction": -0.322949408741848,
          "flux": 0.57,
          "momentum_20j": -0.088,
          "rsi": 38.0,
          "breakout": -0.86,
          "skew": -1.0
        },
        "iv_contrat": 0.377,
        "vol_realisee": 0.315,
        "spot": 14.17
      }
    },
    {
      "ticker": "WBD",
      "kind": "achat_call",
      "strategy": "ACHETER call 28 exp 2026-08-07 @ ~0.54$ (54$/contrat, perte max = la prime)",
      "score": 51.4,
      "summary": "WBD : 3/4 signaux hausse convergents (flux +9%, momentum +3.8%, RSI 56, skew +1.00) → call 28 (21j) @ 0.54$ — si mouvement 1σ (8.3%) : +177% sur la prime",
      "details": {
        "sens": "HAUSSE",
        "side": "call",
        "strike": 28.0,
        "expiry": "2026-08-07",
        "dte": 21,
        "prime_par_action": 0.54,
        "cout_par_contrat": 54,
        "delta": 0.45,
        "breakeven": 28.54,
        "mouvement_necessaire": 0.048,
        "mouvement_attendu_1sigma": 0.083,
        "gain_si_mouvement_1sigma": 1.77,
        "prob_profit_a_echeance": 0.27,
        "score_direction": 0.44,
        "signaux": {
          "direction": 0.43541077216359014,
          "flux": 0.09,
          "momentum_20j": 0.038,
          "rsi": 56.0,
          "breakout": 0.65,
          "skew": 1.0
        },
        "iv_contrat": 0.523,
        "vol_realisee": 0.195,
        "spot": 27.25,
        "attention_earnings": "résultats dans 20j, avant l'expiration : tu paies l'IV gonflée et elle s'écrasera après l'annonce (IV crush)"
      }
    },
    {
      "ticker": "NIO",
      "kind": "put_cash_secured",
      "strategy": "Vendre put NIO 4.5 exp 2026-08-28 @ ~0.23$ (capital requis 450$)",
      "score": 50.0,
      "summary": "NIO : put 4.5 (42j, delta 0.32) rapporte ~41% annualisé, prob. de profit ~61%",
      "details": {
        "expiry": "2026-08-28",
        "dte": 42,
        "strike": 4.5,
        "mid": 0.23,
        "bid_vente": 0.22,
        "commission_incluse": 1.0,
        "delta": 0.32,
        "annual_yield": 0.406,
        "prob_profit": 0.61,
        "capital_requis": 450,
        "greeks": {
          "delta": 0.3176,
          "gamma": -0.3692,
          "theta_jour": 0.0039
        }
      }
    },
    {
      "ticker": "F",
      "kind": "put_cash_secured",
      "strategy": "Vendre put F 13.5 exp 2026-08-07 @ ~0.28$ (capital requis 1,350$)",
      "score": 48.9,
      "summary": "F : put 13.5 (21j, delta 0.27) rapporte ~32% annualisé, prob. de profit ~69%",
      "details": {
        "expiry": "2026-08-07",
        "dte": 21,
        "strike": 13.5,
        "mid": 0.28,
        "bid_vente": 0.26,
        "commission_incluse": 1.0,
        "delta": 0.27,
        "annual_yield": 0.322,
        "prob_profit": 0.69,
        "capital_requis": 1350,
        "greeks": {
          "delta": 0.2703,
          "gamma": -0.2089,
          "theta_jour": 0.012
        }
      }
    },
    {
      "ticker": "QQQ",
      "kind": "put_cash_secured",
      "strategy": "Vendre put QQQ 684 exp 2026-07-31 @ ~10.12$ (capital requis 68,400$)",
      "score": 48.4,
      "summary": "QQQ : put 684 (14j, delta 0.37) rapporte ~38% annualisé, prob. de profit ~61%",
      "details": {
        "expiry": "2026-07-31",
        "dte": 14,
        "strike": 684.0,
        "mid": 10.12,
        "bid_vente": 10.07,
        "commission_incluse": 1.0,
        "delta": 0.37,
        "annual_yield": 0.383,
        "prob_profit": 0.61,
        "capital_requis": 68400,
        "greeks": {
          "delta": 0.368,
          "gamma": -0.0107,
          "theta_jour": 0.4437
        }
      }
    },
    {
      "ticker": "NVDA",
      "kind": "activite_inhabituelle",
      "strategy": "Surveiller / suivre le flux : call 200 exp 2026-07-22",
      "score": 48.0,
      "summary": "NVDA : volume 1,875 vs OI 497 (x3.8) sur call 200 (-1.4% du spot), ~1.09M$ de prime — flux haussier",
      "details": {
        "expiry": "2026-07-22",
        "dte": 5,
        "side": "call",
        "strike": 200.0,
        "volume": 1875,
        "open_interest": 497,
        "ratio_vol_oi": 3.77,
        "premium_flow_usd": 1087500
      }
    },
    {
      "ticker": "SOFI",
      "kind": "prime_riche",
      "strategy": "Vente de prime : put cash-secured, covered call ou iron condor",
      "score": 47.5,
      "summary": "SOFI : IV 71% vs vol réalisée 45% (ratio x1.56) — les options sont chères, avantage au vendeur",
      "details": {
        "iv_atm": 0.707,
        "rv_20d": 0.4536,
        "ratio": 1.56
      }
    },
    {
      "ticker": "PLUG",
      "kind": "achat_put",
      "strategy": "ACHETER put 2 exp 2026-08-07 @ ~0.12$ (12$/contrat, perte max = la prime)",
      "score": 46.2,
      "summary": "PLUG : 3/4 signaux baisse convergents (flux +67%, momentum -17.9%, RSI 31, skew -1.00) → put 2 (21j) @ 0.12$ — si mouvement 1σ (18.1%) : +83% sur la prime",
      "details": {
        "sens": "BAISSE",
        "side": "put",
        "strike": 2.0,
        "expiry": "2026-08-07",
        "dte": 21,
        "prime_par_action": 0.12,
        "cout_par_contrat": 12,
        "delta": 0.31,
        "breakeven": 1.88,
        "mouvement_necessaire": -0.136,
        "mouvement_attendu_1sigma": -0.181,
        "gain_si_mouvement_1sigma": 0.83,
        "prob_profit_a_echeance": 0.24,
        "score_direction": -0.37,
        "signaux": {
          "direction": -0.3745076764029324,
          "flux": 0.67,
          "momentum_20j": -0.179,
          "rsi": 31.0,
          "breakout": -0.93,
          "skew": -1.0
        },
        "iv_contrat": 0.953,
        "vol_realisee": 0.555,
        "spot": 2.17
      }
    },
    {
      "ticker": "TSLA",
      "kind": "activite_inhabituelle",
      "strategy": "Surveiller / suivre le flux : call 360 exp 2026-07-24",
      "score": 45.9,
      "summary": "TSLA : volume 502 vs OI 166 (x3.0) sur call 360 (-5.3% du spot), ~1.33M$ de prime — flux haussier",
      "details": {
        "expiry": "2026-07-24",
        "dte": 7,
        "side": "call",
        "strike": 360.0,
        "volume": 502,
        "open_interest": 166,
        "ratio_vol_oi": 3.02,
        "premium_flow_usd": 1325280
      }
    },
    {
      "ticker": "RIOT",
      "kind": "achat_put",
      "strategy": "ACHETER put 18 exp 2026-08-07 @ ~1.56$ (155$/contrat, perte max = la prime)",
      "score": 45.3,
      "summary": "RIOT : 2/4 signaux baisse convergents (flux +11%, momentum -32.9%, RSI 27, skew +0.37) → put 18 (21j) @ 1.56$ — si mouvement 1σ (19.2%) : +101% sur la prime",
      "details": {
        "sens": "BAISSE",
        "side": "put",
        "strike": 18.0,
        "expiry": "2026-08-07",
        "dte": 21,
        "prime_par_action": 1.56,
        "cout_par_contrat": 155,
        "delta": 0.41,
        "breakeven": 16.45,
        "mouvement_necessaire": -0.107,
        "mouvement_attendu_1sigma": -0.192,
        "gain_si_mouvement_1sigma": 1.01,
        "prob_profit_a_echeance": 0.31,
        "score_direction": -0.33,
        "signaux": {
          "direction": -0.3332264641145022,
          "flux": 0.11,
          "momentum_20j": -0.329,
          "rsi": 27.0,
          "breakout": -1.0,
          "skew": 0.37
        },
        "iv_contrat": 0.986,
        "vol_realisee": 0.688,
        "spot": 18.42,
        "attention_earnings": "résultats dans 13j, avant l'expiration : tu paies l'IV gonflée et elle s'écrasera après l'annonce (IV crush)"
      }
    },
    {
      "ticker": "TLRY",
      "kind": "achat_put",
      "strategy": "ACHETER put 4 exp 2026-08-07 @ ~0.24$ (23$/contrat, perte max = la prime)",
      "score": 41.7,
      "summary": "TLRY : 3/4 signaux baisse convergents (flux -16%, momentum -10.1%, RSI 34, skew +0.04) → put 4 (21j) @ 0.24$ — si mouvement 1σ (13.5%) : +31% sur la prime",
      "details": {
        "sens": "BAISSE",
        "side": "put",
        "strike": 4.0,
        "expiry": "2026-08-07",
        "dte": 21,
        "prime_par_action": 0.24,
        "cout_par_contrat": 23,
        "delta": 0.33,
        "breakeven": 3.77,
        "mouvement_necessaire": -0.118,
        "mouvement_attendu_1sigma": -0.135,
        "gain_si_mouvement_1sigma": 0.31,
        "prob_profit_a_echeance": 0.19,
        "score_direction": -0.42,
        "signaux": {
          "direction": -0.41530124898235204,
          "flux": -0.16,
          "momentum_20j": -0.101,
          "rsi": 34.0,
          "breakout": -1.0,
          "skew": 0.04
        },
        "iv_contrat": 0.875,
        "vol_realisee": 0.357,
        "spot": 4.27,
        "attention_earnings": "résultats dans 11j, avant l'expiration : tu paies l'IV gonflée et elle s'écrasera après l'annonce (IV crush)"
      }
    },
    {
      "ticker": "COIN",
      "kind": "prime_riche",
      "strategy": "Vente de prime : put cash-secured, covered call ou iron condor",
      "score": 39.7,
      "summary": "COIN : IV 84% vs vol réalisée 59% (ratio x1.43) — les options sont chères, avantage au vendeur",
      "details": {
        "iv_atm": 0.8428,
        "rv_20d": 0.5898,
        "ratio": 1.43
      }
    },
    {
      "ticker": "AGNC",
      "kind": "put_cash_secured",
      "strategy": "Vendre put AGNC 11 exp 2026-08-07 @ ~0.17$ (capital requis 1,100$)",
      "score": 38.9,
      "summary": "AGNC : put 11 (21j, delta 0.34) rapporte ~22% annualisé, prob. de profit ~64%",
      "details": {
        "expiry": "2026-08-07",
        "dte": 21,
        "strike": 11.0,
        "mid": 0.17,
        "bid_vente": 0.15,
        "commission_incluse": 1.0,
        "delta": 0.34,
        "annual_yield": 0.221,
        "prob_profit": 0.64,
        "capital_requis": 1100,
        "greeks": {
          "delta": 0.3389,
          "gamma": -0.4685,
          "theta_jour": 0.0063
        }
      }
    },
    {
      "ticker": "RIOT",
      "kind": "prime_riche",
      "strategy": "Vente de prime : put cash-secured, covered call ou iron condor",
      "score": 38.7,
      "summary": "RIOT : IV 97% vs vol réalisée 69% (ratio x1.41) — les options sont chères, avantage au vendeur",
      "details": {
        "iv_atm": 0.9722,
        "rv_20d": 0.6884,
        "ratio": 1.41
      }
    },
    {
      "ticker": "BAC",
      "kind": "put_cash_secured",
      "strategy": "Vendre put BAC 61 exp 2026-08-07 @ ~0.86$ (capital requis 6,100$)",
      "score": 38.7,
      "summary": "BAC : put 61 (21j, delta 0.36) rapporte ~24% annualisé, prob. de profit ~62%",
      "details": {
        "expiry": "2026-08-07",
        "dte": 21,
        "strike": 61.0,
        "mid": 0.86,
        "bid_vente": 0.84,
        "commission_incluse": 1.0,
        "delta": 0.36,
        "annual_yield": 0.236,
        "prob_profit": 0.62,
        "capital_requis": 6100,
        "greeks": {
          "delta": 0.3637,
          "gamma": -0.1214,
          "theta_jour": 0.0248
        }
      }
    },
    {
      "ticker": "RIVN",
      "kind": "options_bon_marche",
      "strategy": "Achat d'options pas chères : calls/puts longs ou straddle",
      "score": 38.1,
      "summary": "RIVN : IV 79% sous la vol réalisée 104% (ratio x0.76) — le marché sous-estime le mouvement",
      "details": {
        "iv_atm": 0.7905,
        "rv_20d": 1.0379,
        "ratio": 0.76
      }
    },
    {
      "ticker": "AGNC",
      "kind": "prime_riche",
      "strategy": "Vente de prime : put cash-secured, covered call ou iron condor",
      "score": 37.9,
      "summary": "AGNC : IV 26% vs vol réalisée 19% (ratio x1.40) — les options sont chères, avantage au vendeur",
      "details": {
        "iv_atm": 0.2598,
        "rv_20d": 0.1859,
        "ratio": 1.4
      }
    },
    {
      "ticker": "SPY",
      "kind": "put_cash_secured",
      "strategy": "Vendre put SPY 739 exp 2026-07-31 @ ~6.07$ (capital requis 73,900$)",
      "score": 37.1,
      "summary": "SPY : put 739 (14j, delta 0.37) rapporte ~21% annualisé, prob. de profit ~62%",
      "details": {
        "expiry": "2026-07-31",
        "dte": 14,
        "strike": 739.0,
        "mid": 6.07,
        "bid_vente": 6.05,
        "commission_incluse": 1.0,
        "delta": 0.37,
        "annual_yield": 0.213,
        "prob_profit": 0.62,
        "capital_requis": 73900,
        "greeks": {
          "delta": 0.3673,
          "gamma": -0.0182,
          "theta_jour": 0.2442
        }
      }
    },
    {
      "ticker": "T",
      "kind": "put_cash_secured",
      "strategy": "Vendre put T 21.5 exp 2026-08-28 @ ~0.61$ (capital requis 2,150$)",
      "score": 36.3,
      "summary": "T : put 21.5 (42j, delta 0.34) rapporte ~21% annualisé, prob. de profit ~61%",
      "details": {
        "expiry": "2026-08-28",
        "dte": 42,
        "strike": 21.5,
        "mid": 0.61,
        "bid_vente": 0.53,
        "commission_incluse": 1.0,
        "delta": 0.34,
        "annual_yield": 0.21,
        "prob_profit": 0.61,
        "capital_requis": 2150,
        "greeks": {
          "delta": 0.3421,
          "gamma": -0.1406,
          "theta_jour": 0.0104
        }
      }
    },
    {
      "ticker": "VALE",
      "kind": "prime_riche",
      "strategy": "Vente de prime : put cash-secured, covered call ou iron condor",
      "score": 36.3,
      "summary": "VALE : IV 43% vs vol réalisée 32% (ratio x1.37) — les options sont chères, avantage au vendeur",
      "details": {
        "iv_atm": 0.4321,
        "rv_20d": 0.3152,
        "ratio": 1.37
      }
    },
    {
      "ticker": "PFE",
      "kind": "put_cash_secured",
      "strategy": "Vendre put PFE 24.5 exp 2026-08-28 @ ~0.55$ (capital requis 2,450$)",
      "score": 36.1,
      "summary": "PFE : put 24.5 (42j, delta 0.32) rapporte ~18% annualisé, prob. de profit ~64%",
      "details": {
        "expiry": "2026-08-28",
        "dte": 42,
        "strike": 24.5,
        "mid": 0.55,
        "bid_vente": 0.52,
        "commission_incluse": 1.0,
        "delta": 0.32,
        "annual_yield": 0.181,
        "prob_profit": 0.64,
        "capital_requis": 2450,
        "greeks": {
          "delta": 0.3228,
          "gamma": -0.1495,
          "theta_jour": 0.0092
        }
      }
    },
    {
      "ticker": "NIO",
      "kind": "prime_riche",
      "strategy": "Vente de prime : put cash-secured, covered call ou iron condor",
      "score": 35.6,
      "summary": "NIO : IV 54% vs vol réalisée 40% (ratio x1.36) — les options sont chères, avantage au vendeur",
      "details": {
        "iv_atm": 0.543,
        "rv_20d": 0.3992,
        "ratio": 1.36
      }
    },
    {
      "ticker": "RIVN",
      "kind": "strategie_optimale",
      "strategy": "ACHETER call 17 + ACHETER put 17 exp 2026-08-28 (débit ~3.43$)",
      "score": 7.0,
      "summary": "RIVN : straddle acheté 17/17 exp 2026-08-28 (42j) — débit 3.43$, risque max 3.43$, POP 52%, EV prudent +0.48$/action, gain max -100% du risque en 42j [ATTENTION : earnings avant l'expiration]",
      "details": {
        "strategie": "straddle acheté",
        "jambes": [
          "ACHETER call 17",
          "ACHETER put 17"
        ],
        "expiry": "2026-08-28",
        "dte": 42,
        "credit_par_action": -3.43,
        "risque_max_par_action": 3.43,
        "prob_profit": 0.522,
        "esperance_gain_EV": 0.848,
        "edge_par_risque": 0.247,
        "ratio_gain_risque": -1.0,
        "rendement_annualise": -8.69,
        "kelly_pleine": 0.0,
        "demi_kelly_conseillee": 0.0,
        "spot": 16.93,
        "vol_estimee": 0.939,
        "iv_atm": 0.791,
        "ev_prudent_apres_frais": 0.484,
        "greeks": {
          "delta": 0.1299,
          "gamma": 0.146,
          "theta_jour": -0.0503,
          "vega": 0.0452
        },
        "attention_earnings": "résultats dans 13j, avant l'expiration — risque de gap"
      }
    },
    {
      "ticker": "RIVN",
      "kind": "strategie_optimale",
      "strategy": "ACHETER call 17 + ACHETER put 17 exp 2026-07-24 (débit ~1.23$)",
      "score": 0.0,
      "summary": "RIVN : straddle acheté 17/17 exp 2026-07-24 (7j) — débit 1.23$, risque max 1.23$, POP 58%, EV prudent +0.39$/action, gain max -100% du risque en 7j",
      "details": {
        "strategie": "straddle acheté",
        "jambes": [
          "ACHETER call 17",
          "ACHETER put 17"
        ],
        "expiry": "2026-07-24",
        "dte": 7,
        "credit_par_action": -1.23,
        "risque_max_par_action": 1.23,
        "prob_profit": 0.578,
        "esperance_gain_EV": 0.529,
        "edge_par_risque": 0.43,
        "ratio_gain_risque": -1.0,
        "rendement_annualise": -52.143,
        "kelly_pleine": 0.0,
        "demi_kelly_conseillee": 0.0,
        "spot": 16.93,
        "vol_estimee": 0.939,
        "iv_atm": 0.791,
        "ev_prudent_apres_frais": 0.386,
        "greeks": {
          "delta": 0.0337,
          "gamma": 0.362,
          "theta_jour": -0.1252,
          "vega": 0.0187
        }
      }
    },
    {
      "ticker": "PBR",
      "kind": "strategie_optimale",
      "strategy": "ACHETER call 18 + ACHETER put 18 exp 2026-07-24 (débit ~0.66$)",
      "score": 0.0,
      "summary": "PBR : straddle acheté 18/18 exp 2026-07-24 (7j) — débit 0.66$, risque max 0.66$, POP 50%, EV prudent +0.02$/action, gain max -100% du risque en 7j",
      "details": {
        "strategie": "straddle acheté",
        "jambes": [
          "ACHETER call 18",
          "ACHETER put 18"
        ],
        "expiry": "2026-07-24",
        "dte": 7,
        "credit_par_action": -0.66,
        "risque_max_par_action": 0.66,
        "prob_profit": 0.498,
        "esperance_gain_EV": 0.107,
        "edge_par_risque": 0.163,
        "ratio_gain_risque": -1.0,
        "rendement_annualise": -52.143,
        "kelly_pleine": 0.0,
        "demi_kelly_conseillee": 0.0,
        "spot": 17.79,
        "vol_estimee": 0.377,
        "iv_atm": 0.526,
        "ev_prudent_apres_frais": 0.021,
        "greeks": {
          "delta": -0.1443,
          "gamma": 0.8441,
          "theta_jour": -0.0517,
          "vega": 0.0193
        }
      }
    }
  ]
}